{
"meta":{"test_sets":[],"test_metrics":[],"learn_metrics":[{"best_value":"Min","name":"RMSE"}],"launch_mode":"Train","parameters":"","iteration_count":937,"learn_sets":["learn"],"name":"experiment"},
"iterations":[
{"learn":[25.43287114],"iteration":0,"passed_time":0.001039097428,"remaining_time":0.9725951926},
{"learn":[25.39422319],"iteration":1,"passed_time":0.001237884153,"remaining_time":0.5787108417},
{"learn":[25.35757238],"iteration":2,"passed_time":0.00139667194,"remaining_time":0.4348305306},
{"learn":[25.32115611],"iteration":3,"passed_time":0.001597707606,"remaining_time":0.372665299},
{"learn":[25.28332929],"iteration":4,"passed_time":0.00174149579,"remaining_time":0.3246148153},
{"learn":[25.24636038],"iteration":5,"passed_time":0.001967448795,"remaining_time":0.3052824713},
{"learn":[25.20945606],"iteration":6,"passed_time":0.002099778283,"remaining_time":0.2789705434},
{"learn":[25.17167185],"iteration":7,"passed_time":0.002278315546,"remaining_time":0.2645693928},
{"learn":[25.13398702],"iteration":8,"passed_time":0.002476810279,"remaining_time":0.2553866599},
{"learn":[25.10092869],"iteration":9,"passed_time":0.002654096575,"remaining_time":0.2460347525},
{"learn":[25.06544329],"iteration":10,"passed_time":0.002867632909,"remaining_time":0.2414025521},
{"learn":[25.02819492],"iteration":11,"passed_time":0.003025587717,"remaining_time":0.2332223866},
{"learn":[24.99247858],"iteration":12,"passed_time":0.003289455716,"remaining_time":0.2338043909},
{"learn":[24.95738919],"iteration":13,"passed_time":0.003700152818,"remaining_time":0.2439457894},
{"learn":[24.92154549],"iteration":14,"passed_time":0.003975812504,"remaining_time":0.2443799419},
{"learn":[24.88461277],"iteration":15,"passed_time":0.004102351146,"remaining_time":0.2361415878},
{"learn":[24.84942198],"iteration":16,"passed_time":0.004264429845,"remaining_time":0.2307809093},
{"learn":[24.8127555],"iteration":17,"passed_time":0.004445425043,"remaining_time":0.2269636452},
{"learn":[24.77866821],"iteration":18,"passed_time":0.00464450376,"remaining_time":0.2244028659},
{"learn":[24.74599907],"iteration":19,"passed_time":0.004766875513,"remaining_time":0.2185612423},
{"learn":[24.71131857],"iteration":20,"passed_time":0.004914663592,"remaining_time":0.2143729452},
{"learn":[24.67725044],"iteration":21,"passed_time":0.005084284091,"remaining_time":0.2114599974},
{"learn":[24.64283285],"iteration":22,"passed_time":0.005275946005,"remaining_time":0.2096615065},
{"learn":[24.60855274],"iteration":23,"passed_time":0.005400567698,"remaining_time":0.2054465962},
{"learn":[24.57298495],"iteration":24,"passed_time":0.005565647318,"remaining_time":0.2030348142},
{"learn":[24.53733163],"iteration":25,"passed_time":0.005754934296,"remaining_time":0.201644044},
{"learn":[24.502919],"iteration":26,"passed_time":0.005934971518,"remaining_time":0.2000305215},
{"learn":[24.47325171],"iteration":27,"passed_time":0.00609317532,"remaining_time":0.1978105845},
{"learn":[24.44100837],"iteration":28,"passed_time":0.006326169138,"remaining_time":0.1980745372},
{"learn":[24.40584427],"iteration":29,"passed_time":0.006566245768,"remaining_time":0.198519497},
{"learn":[24.37241831],"iteration":30,"passed_time":0.006786822915,"remaining_time":0.1983503729},
{"learn":[24.33750999],"iteration":31,"passed_time":0.006996984338,"remaining_time":0.1978834633},
{"learn":[24.30378954],"iteration":32,"passed_time":0.007191104187,"remaining_time":0.1969926723},
{"learn":[24.26914454],"iteration":33,"passed_time":0.007416890196,"remaining_time":0.1969838779},
{"learn":[24.23484991],"iteration":34,"passed_time":0.007678049267,"remaining_time":0.1978742982},
{"learn":[24.20477401],"iteration":35,"passed_time":0.007888126692,"remaining_time":0.1974222819},
{"learn":[24.17050327],"iteration":36,"passed_time":0.008078121651,"remaining_time":0.196494851},
{"learn":[24.1387032],"iteration":37,"passed_time":0.008267574624,"remaining_time":0.1955934102},
{"learn":[24.10484817],"iteration":38,"passed_time":0.008540775375,"remaining_time":0.1966568279},
{"learn":[24.07096347],"iteration":39,"passed_time":0.008718228666,"remaining_time":0.1955062778},
{"learn":[24.03721182],"iteration":40,"passed_time":0.008965055117,"remaining_time":0.1959192533},
{"learn":[24.00417762],"iteration":41,"passed_time":0.00907571818,"remaining_time":0.1933992326},
{"learn":[23.97132373],"iteration":42,"passed_time":0.009211131587,"remaining_time":0.1915058521},
{"learn":[23.93956875],"iteration":43,"passed_time":0.009342378104,"remaining_time":0.1896078102},
{"learn":[23.90631768],"iteration":44,"passed_time":0.009480958427,"remaining_time":0.1879336648},
{"learn":[23.87340513],"iteration":45,"passed_time":0.00958787259,"remaining_time":0.1857129234},
{"learn":[23.84100798],"iteration":46,"passed_time":0.009692744808,"remaining_time":0.1835434655},
{"learn":[23.80813784],"iteration":47,"passed_time":0.009790534213,"remaining_time":0.1813288524},
{"learn":[23.77683484],"iteration":48,"passed_time":0.01053972233,"remaining_time":0.1910055802},
{"learn":[23.75008087],"iteration":49,"passed_time":0.0107446339,"remaining_time":0.1906098053},
{"learn":[23.72204369],"iteration":50,"passed_time":0.01099546124,"remaining_time":0.1910191894},
{"learn":[23.69277688],"iteration":51,"passed_time":0.01116062386,"remaining_time":0.189945233},
{"learn":[23.66533719],"iteration":52,"passed_time":0.01137332621,"remaining_time":0.1896984976},
{"learn":[23.6328537],"iteration":53,"passed_time":0.01153444694,"remaining_time":0.1886095675},
{"learn":[23.60295589],"iteration":54,"passed_time":0.01169881758,"remaining_time":0.1876064928},
{"learn":[23.57317476],"iteration":55,"passed_time":0.01180943964,"remaining_time":0.1857877915},
{"learn":[23.54350995],"iteration":56,"passed_time":0.01209930695,"remaining_time":0.1867963178},
{"learn":[23.51396109],"iteration":57,"passed_time":0.01237225771,"remaining_time":0.1875036987},
{"learn":[23.48452782],"iteration":58,"passed_time":0.01260475154,"remaining_time":0.1875757941},
{"learn":[23.45676868],"iteration":59,"passed_time":0.01281987083,"remaining_time":0.1873837786},
{"learn":[23.42977476],"iteration":60,"passed_time":0.01300286598,"remaining_time":0.1867296819},
{"learn":[23.40063524],"iteration":61,"passed_time":0.01314452822,"remaining_time":0.1855074547},
{"learn":[23.36936053],"iteration":62,"passed_time":0.01329044134,"remaining_time":0.1843785037},
{"learn":[23.34140831],"iteration":63,"passed_time":0.01342122887,"remaining_time":0.1830739501},
{"learn":[23.31356699],"iteration":64,"passed_time":0.01356205814,"remaining_time":0.1819402261},
{"learn":[23.28484788],"iteration":65,"passed_time":0.0136614725,"remaining_time":0.1802900386},
{"learn":[23.25624173],"iteration":66,"passed_time":0.01387500883,"remaining_time":0.1801680251},
{"learn":[23.22741741],"iteration":67,"passed_time":0.01403962947,"remaining_time":0.179418206},
{"learn":[23.19871418],"iteration":68,"passed_time":0.0141437107,"remaining_time":0.177923781},
{"learn":[23.16819885],"iteration":69,"passed_time":0.01434183045,"remaining_time":0.1776338142},
{"learn":[23.13890071],"iteration":70,"passed_time":0.01451382588,"remaining_time":0.1770277917},
{"learn":[23.10861637],"iteration":71,"passed_time":0.0146564881,"remaining_time":0.1760814195},
{"learn":[23.07845384],"iteration":72,"passed_time":0.01484735803,"remaining_time":0.1757276348},
{"learn":[23.05351051],"iteration":73,"passed_time":0.01501943747,"remaining_time":0.1751591153},
{"learn":[23.02764801],"iteration":74,"passed_time":0.01516943349,"remaining_time":0.1743473555},
{"learn":[22.99916036],"iteration":75,"passed_time":0.01535692851,"remaining_time":0.1739778348},
{"learn":[22.97160003],"iteration":76,"passed_time":0.0155307159,"remaining_time":0.1734599438},
{"learn":[22.94414894],"iteration":77,"passed_time":0.01564625383,"remaining_time":0.1723093852},
{"learn":[22.91481318],"iteration":78,"passed_time":0.01581358339,"remaining_time":0.171747526},
{"learn":[22.88996724],"iteration":79,"passed_time":0.01599403761,"remaining_time":0.1713361279},
{"learn":[22.86322923],"iteration":80,"passed_time":0.0161526164,"remaining_time":0.1706992548},
{"learn":[22.83420535],"iteration":81,"passed_time":0.01629694657,"remaining_time":0.1699254795},
{"learn":[22.80507964],"iteration":82,"passed_time":0.01646956699,"remaining_time":0.1694579543},
{"learn":[22.77929887],"iteration":83,"passed_time":0.01663781252,"remaining_time":0.1689530248},
{"learn":[22.75473251],"iteration":84,"passed_time":0.01677218396,"remaining_time":0.1681164792},
{"learn":[22.72774709],"iteration":85,"passed_time":0.01690580541,"remaining_time":0.1672888419},
{"learn":[22.69891723],"iteration":86,"passed_time":0.01705505145,"remaining_time":0.166629813},
{"learn":[22.67004311],"iteration":87,"passed_time":0.01721179729,"remaining_time":0.1660547262},
{"learn":[22.64284548],"iteration":88,"passed_time":0.01737175205,"remaining_time":0.165519615},
{"learn":[22.61443001],"iteration":89,"passed_time":0.0174601667,"remaining_time":0.1643195689},
{"learn":[22.58825654],"iteration":90,"passed_time":0.0176110787,"remaining_time":0.1637249734},
{"learn":[22.55997568],"iteration":91,"passed_time":0.01783857266,"remaining_time":0.1638434119},
{"learn":[22.53189082],"iteration":92,"passed_time":0.01794998671,"remaining_time":0.1629009546},
{"learn":[22.50520099],"iteration":93,"passed_time":0.01818414749,"remaining_time":0.1630769823},
{"learn":[22.48139443],"iteration":94,"passed_time":0.01832010188,"remaining_time":0.1623739557},
{"learn":[22.45360609],"iteration":95,"passed_time":0.01844093268,"remaining_time":0.161550254},
{"learn":[22.4259315],"iteration":96,"passed_time":0.01863159462,"remaining_time":0.1613457678},
{"learn":[22.3983703],"iteration":97,"passed_time":0.01893837848,"remaining_time":0.1621357096},
{"learn":[22.37216734],"iteration":98,"passed_time":0.01909629129,"remaining_time":0.1616433545},
{"learn":[22.34852173],"iteration":99,"passed_time":0.01925662103,"remaining_time":0.1611779181},
{"learn":[22.32288788],"iteration":100,"passed_time":0.01942807549,"remaining_time":0.160810605},
{"learn":[22.29569787],"iteration":101,"passed_time":0.0196045288,"remaining_time":0.1604880544},
{"learn":[22.26861964],"iteration":102,"passed_time":0.01976256561,"remaining_time":0.1600192206},
{"learn":[22.24643508],"iteration":103,"passed_time":0.01988868726,"remaining_time":0.1593007355},
{"learn":[22.21955131],"iteration":104,"passed_time":0.02002155874,"remaining_time":0.1586470178},
{"learn":[22.19277831],"iteration":105,"passed_time":0.02015993007,"remaining_time":0.1580462442},
{"learn":[22.16611571],"iteration":106,"passed_time":0.02032388472,"remaining_time":0.1576525637},
{"learn":[22.14246522],"iteration":107,"passed_time":0.0204562562,"remaining_time":0.1570207073},
{"learn":[22.11718596],"iteration":108,"passed_time":0.0205620034,"remaining_time":0.1561957689},
{"learn":[22.09201395],"iteration":109,"passed_time":0.02067012553,"remaining_time":0.1554017619},
{"learn":[22.0657414],"iteration":110,"passed_time":0.02077512274,"remaining_time":0.1545968593},
{"learn":[22.03932228],"iteration":111,"passed_time":0.0208859948,"remaining_time":0.1538477296},
{"learn":[22.01444342],"iteration":112,"passed_time":0.02099786683,"remaining_time":0.1531171882},
{"learn":[21.98847751],"iteration":113,"passed_time":0.02109986413,"remaining_time":0.1523262121},
{"learn":[21.96261932],"iteration":114,"passed_time":0.021217819,"remaining_time":0.1516612801},
{"learn":[21.93965995],"iteration":115,"passed_time":0.02133031601,"remaining_time":0.1509671504},
{"learn":[21.91399987],"iteration":116,"passed_time":0.02154897621,"remaining_time":0.1510270127},
{"learn":[21.88844647],"iteration":117,"passed_time":0.02168672255,"remaining_time":0.1505205574},
{"learn":[21.86411869],"iteration":118,"passed_time":0.02184650931,"remaining_time":0.1501718035},
{"learn":[21.83989482],"iteration":119,"passed_time":0.02200442212,"remaining_time":0.1498134406},
{"learn":[21.81436394],"iteration":120,"passed_time":0.02216979274,"remaining_time":0.1495086849},
{"learn":[21.78920013],"iteration":121,"passed_time":0.02230466416,"remaining_time":0.1490024696},
{"learn":[21.76693557],"iteration":122,"passed_time":0.02240907839,"remaining_time":0.1483007301},
{"learn":[21.74196586],"iteration":123,"passed_time":0.02250499284,"remaining_time":0.1475528966},
{"learn":[21.71894361],"iteration":124,"passed_time":0.0226310725,"remaining_time":0.1470114469},
{"learn":[21.6941687],"iteration":125,"passed_time":0.0227476524,"remaining_time":0.1464154452},
{"learn":[21.66926387],"iteration":126,"passed_time":0.02286427431,"remaining_time":0.1458272613},
{"learn":[21.64651543],"iteration":127,"passed_time":0.02296539662,"remaining_time":0.1451484834},
{"learn":[21.62177582],"iteration":128,"passed_time":0.02310689287,"remaining_time":0.144731546},
{"learn":[21.60067964],"iteration":129,"passed_time":0.02323184755,"remaining_time":0.1442161614},
{"learn":[21.57654809],"iteration":130,"passed_time":0.02335526128,"remaining_time":0.1436972564},
{"learn":[21.5556095],"iteration":131,"passed_time":0.02353758944,"remaining_time":0.1435436326},
{"learn":[21.53147121],"iteration":132,"passed_time":0.02368137763,"remaining_time":0.1431565986},
{"learn":[21.51422283],"iteration":133,"passed_time":0.02381208316,"remaining_time":0.1426947968},
{"learn":[21.49096173],"iteration":134,"passed_time":0.02393249696,"remaining_time":0.1421767597},
{"learn":[21.47127868],"iteration":135,"passed_time":0.02407195226,"remaining_time":0.1417767188},
{"learn":[21.44723277],"iteration":136,"passed_time":0.0242099486,"remaining_time":0.1413719626},
{"learn":[21.42451842],"iteration":137,"passed_time":0.02433915317,"remaining_time":0.1409201695},
{"learn":[21.40063235],"iteration":138,"passed_time":0.02448010743,"remaining_time":0.1405404729},
{"learn":[21.37886225],"iteration":139,"passed_time":0.02460543811,"remaining_time":0.1400752441},
{"learn":[21.35515998],"iteration":140,"passed_time":0.02475822605,"remaining_time":0.1397698435},
{"learn":[21.33346629],"iteration":141,"passed_time":0.02492722157,"remaining_time":0.139557332},
{"learn":[21.31297401],"iteration":142,"passed_time":0.02508096749,"remaining_time":0.1392607565},
{"learn":[21.28975054],"iteration":143,"passed_time":0.02520783912,"remaining_time":0.1388181696},
{"learn":[21.26869654],"iteration":144,"passed_time":0.02531900317,"remaining_time":0.1382941415},
{"learn":[21.24563549],"iteration":145,"passed_time":0.02542850027,"remaining_time":0.1377667377},
{"learn":[21.22417265],"iteration":146,"passed_time":0.02554858108,"remaining_time":0.1373018983},
{"learn":[21.2037777],"iteration":147,"passed_time":0.02567307778,"remaining_time":0.1368652592},
{"learn":[21.18117084],"iteration":148,"passed_time":0.02577636704,"remaining_time":0.1363206525},
{"learn":[21.15941368],"iteration":149,"passed_time":0.02589286395,"remaining_time":0.1358512262},
{"learn":[21.13654154],"iteration":150,"passed_time":0.02602531843,"remaining_time":0.1354695383},
{"learn":[21.11571699],"iteration":151,"passed_time":0.02612481579,"remaining_time":0.1349209237},
{"learn":[21.09577856],"iteration":152,"passed_time":0.02624189568,"remaining_time":0.1344682759},
{"learn":[21.07643455],"iteration":153,"passed_time":0.02633347625,"remaining_time":0.1338903371},
{"learn":[21.05702722],"iteration":154,"passed_time":0.0264408484,"remaining_time":0.1333983449},
{"learn":[21.03648207],"iteration":155,"passed_time":0.02653551289,"remaining_time":0.1328476639},
{"learn":[21.01602234],"iteration":156,"passed_time":0.02663430127,"remaining_time":0.1323232802},
{"learn":[20.99368914],"iteration":157,"passed_time":0.02681221255,"remaining_time":0.1321943897},
{"learn":[20.9742492],"iteration":158,"passed_time":0.02693441731,"remaining_time":0.1317923061},
{"learn":[20.95324293],"iteration":159,"passed_time":0.0270628719,"remaining_time":0.1314240717},
{"learn":[20.93206841],"iteration":160,"passed_time":0.02719520239,"remaining_time":0.1310774972},
{"learn":[20.9118639],"iteration":161,"passed_time":0.02732457396,"remaining_time":0.1307194124},
{"learn":[20.89204414],"iteration":162,"passed_time":0.02742336233,"remaining_time":0.1302189107},
{"learn":[20.8732589],"iteration":163,"passed_time":0.0275376093,"remaining_time":0.1297961707},
{"learn":[20.85264339],"iteration":164,"passed_time":0.02763635668,"remaining_time":0.1293046507},
{"learn":[20.83303977],"iteration":165,"passed_time":0.02776039439,"remaining_time":0.1289353258},
{"learn":[20.81259274],"iteration":166,"passed_time":0.02788118219,"remaining_time":0.1285539538},
{"learn":[20.79126699],"iteration":167,"passed_time":0.02802101148,"remaining_time":0.1282628442},
{"learn":[20.77108899],"iteration":168,"passed_time":0.02812805064,"remaining_time":0.1278245141},
{"learn":[20.75264799],"iteration":169,"passed_time":0.02822258913,"remaining_time":0.1273336815},
{"learn":[20.73147361],"iteration":170,"passed_time":0.02836171044,"remaining_time":0.1270471941},
{"learn":[20.71317912],"iteration":171,"passed_time":0.02847674938,"remaining_time":0.1266553098},
{"learn":[20.6951567],"iteration":172,"passed_time":0.02862224552,"remaining_time":0.1264011305},
{"learn":[20.67493415],"iteration":173,"passed_time":0.02888169764,"remaining_time":0.126647904},
{"learn":[20.65503708],"iteration":174,"passed_time":0.02900806928,"remaining_time":0.1263094217},
{"learn":[20.63724801],"iteration":175,"passed_time":0.02912323323,"remaining_time":0.1259248891},
{"learn":[20.61878321],"iteration":176,"passed_time":0.02922189761,"remaining_time":0.1254725547},
{"learn":[20.59997175],"iteration":177,"passed_time":0.02936064393,"remaining_time":0.1251951053},
{"learn":[20.58040467],"iteration":178,"passed_time":0.02946247423,"remaining_time":0.1247628797},
{"learn":[20.561007],"iteration":179,"passed_time":0.02959497071,"remaining_time":0.1244632935},
{"learn":[20.54035024],"iteration":180,"passed_time":0.0297123426,"remaining_time":0.1241023812},
{"learn":[20.52264755],"iteration":181,"passed_time":0.02984071419,"remaining_time":0.1237897759},
{"learn":[20.50213925],"iteration":182,"passed_time":0.03000587681,"remaining_time":0.1236307711},
{"learn":[20.48325147],"iteration":183,"passed_time":0.03014729006,"remaining_time":0.1233745077},
{"learn":[20.46288574],"iteration":184,"passed_time":0.03026162002,"remaining_time":0.123009396},
{"learn":[20.44373035],"iteration":185,"passed_time":0.03035224262,"remaining_time":0.1225512592},
{"learn":[20.42375118],"iteration":186,"passed_time":0.03048590607,"remaining_time":0.1222696768},
{"learn":[20.40385879],"iteration":187,"passed_time":0.0306356101,"remaining_time":0.1220535743},
{"learn":[20.38609805],"iteration":188,"passed_time":0.03077998127,"remaining_time":0.1218170687},
{"learn":[20.36611995],"iteration":189,"passed_time":0.03090956083,"remaining_time":0.1215233786},
{"learn":[20.34622868],"iteration":190,"passed_time":0.03102147386,"remaining_time":0.1211624058},
{"learn":[20.32642439],"iteration":191,"passed_time":0.03115851222,"remaining_time":0.1209015188},
{"learn":[20.30803903],"iteration":192,"passed_time":0.03126350944,"remaining_time":0.1205183991},
{"learn":[20.28942255],"iteration":193,"passed_time":0.03135284107,"remaining_time":0.120078149},
{"learn":[20.27352643],"iteration":194,"passed_time":0.03146538008,"remaining_time":0.1197298052},
{"learn":[20.25532423],"iteration":195,"passed_time":0.03156933632,"remaining_time":0.1193514195},
{"learn":[20.23772134],"iteration":196,"passed_time":0.0317283321,"remaining_time":0.1191825673},
{"learn":[20.22069128],"iteration":197,"passed_time":0.03192036901,"remaining_time":0.1191371348},
{"learn":[20.20266107],"iteration":198,"passed_time":0.03206411519,"remaining_time":0.1189111408},
{"learn":[20.18332218],"iteration":199,"passed_time":0.03216273758,"remaining_time":0.118519688},
{"learn":[20.16404626],"iteration":200,"passed_time":0.03227215067,"remaining_time":0.1181706612},
{"learn":[20.14742032],"iteration":201,"passed_time":0.03237023107,"remaining_time":0.1177827715},
{"learn":[20.12842317],"iteration":202,"passed_time":0.03248397805,"remaining_time":0.1174543837},
{"learn":[20.11032575],"iteration":203,"passed_time":0.03262764124,"remaining_time":0.1172355933},
{"learn":[20.09153427],"iteration":204,"passed_time":0.03272938854,"remaining_time":0.1168678654},
{"learn":[20.07282519],"iteration":205,"passed_time":0.03286005107,"remaining_time":0.1166053269},
{"learn":[20.05397891],"iteration":206,"passed_time":0.03299625546,"remaining_time":0.1163636062},
{"learn":[20.03705158],"iteration":207,"passed_time":0.03309004497,"remaining_time":0.1159742442},
{"learn":[20.01834968],"iteration":208,"passed_time":0.03323241619,"remaining_time":0.115756933},
{"learn":[20.00096876],"iteration":209,"passed_time":0.03337637037,"remaining_time":0.1155458155},
{"learn":[19.98244487],"iteration":210,"passed_time":0.0335222415,"remaining_time":0.1153419305},
{"learn":[19.96584683],"iteration":211,"passed_time":0.03369602789,"remaining_time":0.1152340576},
{"learn":[19.94838915],"iteration":212,"passed_time":0.0337899424,"remaining_time":0.1148540765},
{"learn":[19.93003984],"iteration":213,"passed_time":0.03392752275,"remaining_time":0.1146242941},
{"learn":[19.91197787],"iteration":214,"passed_time":0.03404960251,"remaining_time":0.1143433163},
{"learn":[19.89449287],"iteration":215,"passed_time":0.03421489012,"remaining_time":0.114208036},
{"learn":[19.87707724],"iteration":216,"passed_time":0.03433405396,"remaining_time":0.1139194417},
{"learn":[19.85898339],"iteration":217,"passed_time":0.03446209256,"remaining_time":0.1136616723},
{"learn":[19.84117402],"iteration":218,"passed_time":0.03458354734,"remaining_time":0.1133835022},
{"learn":[19.82416015],"iteration":219,"passed_time":0.03468666961,"remaining_time":0.1130470096},
{"learn":[19.80788136],"iteration":220,"passed_time":0.034822708,"remaining_time":0.1128192712},
{"learn":[19.79120634],"iteration":221,"passed_time":0.03491841346,"remaining_time":0.1124624578},
{"learn":[19.77345219],"iteration":222,"passed_time":0.03502711957,"remaining_time":0.1121496115},
{"learn":[19.75690144],"iteration":223,"passed_time":0.03517344869,"remaining_time":0.1119583434},
{"learn":[19.73929668],"iteration":224,"passed_time":0.03526623823,"remaining_time":0.1115980516},
{"learn":[19.72310184],"iteration":225,"passed_time":0.0353690685,"remaining_time":0.1112717155},
{"learn":[19.70580925],"iteration":226,"passed_time":0.03561093708,"remaining_time":0.1113822261},
{"learn":[19.68892077],"iteration":227,"passed_time":0.03576072411,"remaining_time":0.1112033043},
{"learn":[19.67199758],"iteration":228,"passed_time":0.03588767874,"remaining_time":0.1109540461},
{"learn":[19.65623871],"iteration":229,"passed_time":0.03601880026,"remaining_time":0.1107186599},
{"learn":[19.64054767],"iteration":230,"passed_time":0.0361379641,"remaining_time":0.1104476305},
{"learn":[19.62506039],"iteration":231,"passed_time":0.03628666815,"remaining_time":0.1102676769},
{"learn":[19.60838972],"iteration":232,"passed_time":0.03640504001,"remaining_time":0.1099963441},
{"learn":[19.59212682],"iteration":233,"passed_time":0.03650670431,"remaining_time":0.1096761245},
{"learn":[19.57510611],"iteration":234,"passed_time":0.03658916012,"remaining_time":0.1093003847},
{"learn":[19.56009051],"iteration":235,"passed_time":0.03669478232,"remaining_time":0.1089959424},
{"learn":[19.54404527],"iteration":236,"passed_time":0.03679882156,"remaining_time":0.1086885025},
{"learn":[19.52887861],"iteration":237,"passed_time":0.03691302753,"remaining_time":0.1084126313},
{"learn":[19.51420315],"iteration":238,"passed_time":0.03704810695,"remaining_time":0.1081990738},
{"learn":[19.49785921],"iteration":239,"passed_time":0.03717139567,"remaining_time":0.1079519283},
{"learn":[19.48284741],"iteration":240,"passed_time":0.03730818404,"remaining_time":0.1077447971},
{"learn":[19.46707044],"iteration":241,"passed_time":0.03744672237,"remaining_time":0.1075432729},
{"learn":[19.45052987],"iteration":242,"passed_time":0.03754546975,"remaining_time":0.1072286255},
{"learn":[19.43524179],"iteration":243,"passed_time":0.03765834175,"remaining_time":0.1069558641},
{"learn":[19.4210237],"iteration":244,"passed_time":0.03777254772,"remaining_time":0.1066881756},
{"learn":[19.40463768],"iteration":245,"passed_time":0.03790446022,"remaining_time":0.1064714716},
{"learn":[19.38877526],"iteration":246,"passed_time":0.03799999869,"remaining_time":0.1061538425},
{"learn":[19.37251879],"iteration":247,"passed_time":0.0381052459,"remaining_time":0.1058649775},
{"learn":[19.35633696],"iteration":248,"passed_time":0.03822407574,"remaining_time":0.1056151169},
{"learn":[19.34160842],"iteration":249,"passed_time":0.03833986467,"remaining_time":0.1053579481},
{"learn":[19.326887],"iteration":250,"passed_time":0.03847152718,"remaining_time":0.1051452894},
{"learn":[19.31177272],"iteration":251,"passed_time":0.03857106653,"remaining_time":0.1048459547},
{"learn":[19.29597607],"iteration":252,"passed_time":0.03869043837,"remaining_time":0.1046018176},
{"learn":[19.28097012],"iteration":253,"passed_time":0.0387946436,"remaining_time":0.1043178802},
{"learn":[19.26584095],"iteration":254,"passed_time":0.03891089052,"remaining_time":0.1040675582},
{"learn":[19.25044684],"iteration":255,"passed_time":0.03901842966,"remaining_time":0.1037951195},
{"learn":[19.23583931],"iteration":256,"passed_time":0.03915684299,"remaining_time":0.1036056546},
{"learn":[19.22147618],"iteration":257,"passed_time":0.03924996552,"remaining_time":0.1032973899},
{"learn":[19.20623907],"iteration":258,"passed_time":0.03948920917,"remaining_time":0.1033732966},
{"learn":[19.19254816],"iteration":259,"passed_time":0.03958837354,"remaining_time":0.1030820342},
{"learn":[19.17775966],"iteration":260,"passed_time":0.03967862115,"remaining_time":0.102769149},
{"learn":[19.16380918],"iteration":261,"passed_time":0.03979653502,"remaining_time":0.102529241},
{"learn":[19.14907554],"iteration":262,"passed_time":0.03989103251,"remaining_time":0.1022302506},
{"learn":[19.13538694],"iteration":263,"passed_time":0.04015260957,"remaining_time":0.1023587358},
{"learn":[19.12133708],"iteration":264,"passed_time":0.04054418318,"remaining_time":0.1028139287},
{"learn":[19.10707463],"iteration":265,"passed_time":0.04064551349,"remaining_time":0.1025305998},
{"learn":[19.09188461],"iteration":266,"passed_time":0.04076455133,"remaining_time":0.1022930689},
{"learn":[19.0773899],"iteration":267,"passed_time":0.0408862981,"remaining_time":0.1020631844},
{"learn":[19.06309024],"iteration":268,"passed_time":0.04101612866,"remaining_time":0.1018541782},
{"learn":[19.0487395],"iteration":269,"passed_time":0.0411650827,"remaining_time":0.1016930006},
{"learn":[19.03455189],"iteration":270,"passed_time":0.04130162108,"remaining_time":0.1015014009},
{"learn":[19.02025083],"iteration":271,"passed_time":0.04143428456,"remaining_time":0.1013007325},
{"learn":[19.00654845],"iteration":272,"passed_time":0.04222326363,"remaining_time":0.1026968756},
{"learn":[18.99206495],"iteration":273,"passed_time":0.04236075998,"remaining_time":0.102500671},
{"learn":[18.97885162],"iteration":274,"passed_time":0.04249596439,"remaining_time":0.1022993761},
{"learn":[18.96592676],"iteration":275,"passed_time":0.04261171132,"remaining_time":0.1020519608},
{"learn":[18.95267397],"iteration":276,"passed_time":0.04272137441,"remaining_time":0.1017910004},
{"learn":[18.93966962],"iteration":277,"passed_time":0.04280970506,"remaining_time":0.1014805598},
{"learn":[18.92673683],"iteration":278,"passed_time":0.04291336831,"remaining_time":0.1012078722},
{"learn":[18.91198071],"iteration":279,"passed_time":0.04299390818,"remaining_time":0.1008821345},
{"learn":[18.89747825],"iteration":280,"passed_time":0.04308448877,"remaining_time":0.1005815823},
{"learn":[18.88413811],"iteration":281,"passed_time":0.0431854031,"remaining_time":0.1003065214},
{"learn":[18.87109379],"iteration":282,"passed_time":0.04326640095,"remaining_time":0.09998666508},
{"learn":[18.85797412],"iteration":283,"passed_time":0.04342893763,"remaining_time":0.0998559728},
{"learn":[18.84348769],"iteration":284,"passed_time":0.04353401785,"remaining_time":0.09959361276},
{"learn":[18.82997773],"iteration":285,"passed_time":0.04364384793,"remaining_time":0.09934316435},
{"learn":[18.81622035],"iteration":286,"passed_time":0.04374022037,"remaining_time":0.09906321687},
{"learn":[18.80301865],"iteration":287,"passed_time":0.04384884249,"remaining_time":0.09881214853},
{"learn":[18.78868232],"iteration":288,"passed_time":0.04396975628,"remaining_time":0.09858962655},
{"learn":[18.77520892],"iteration":289,"passed_time":0.04405842093,"remaining_time":0.09829585635},
{"learn":[18.76306241],"iteration":290,"passed_time":0.04414312668,"remaining_time":0.09799470734},
{"learn":[18.74888749],"iteration":291,"passed_time":0.04426420747,"remaining_time":0.09777538979},
{"learn":[18.73614687],"iteration":292,"passed_time":0.04435316311,"remaining_time":0.09748613325},
{"learn":[18.72210036],"iteration":293,"passed_time":0.04448649257,"remaining_time":0.09729528818},
{"learn":[18.70862708],"iteration":294,"passed_time":0.04461794708,"remaining_time":0.09710075264},
{"learn":[18.69653688],"iteration":295,"passed_time":0.04471373554,"remaining_time":0.09682940704},
{"learn":[18.68376838],"iteration":296,"passed_time":0.04483869123,"remaining_time":0.09662209557},
{"learn":[18.6698031],"iteration":297,"passed_time":0.04493339771,"remaining_time":0.09635047362},
{"learn":[18.65655516],"iteration":298,"passed_time":0.04503756195,"remaining_time":0.0961002158},
{"learn":[18.64510569],"iteration":299,"passed_time":0.04515772576,"remaining_time":0.09588490437},
{"learn":[18.63285154],"iteration":300,"passed_time":0.04525126528,"remaining_time":0.09561396916},
{"learn":[18.62065178],"iteration":301,"passed_time":0.04535192961,"remaining_time":0.09535918974},
{"learn":[18.60696009],"iteration":302,"passed_time":0.04547009347,"remaining_time":0.09514204377},
{"learn":[18.59333113],"iteration":303,"passed_time":0.04558879932,"remaining_time":0.09492667754},
{"learn":[18.57977446],"iteration":304,"passed_time":0.04571367101,"remaining_time":0.09472472157},
{"learn":[18.56711654],"iteration":305,"passed_time":0.04583300084,"remaining_time":0.09451184161},
{"learn":[18.55496393],"iteration":306,"passed_time":0.04601112112,"remaining_time":0.09442021597},
{"learn":[18.54261881],"iteration":307,"passed_time":0.04611528435,"remaining_time":0.09417699305},
{"learn":[18.53102905],"iteration":308,"passed_time":0.04624061403,"remaining_time":0.09397768806},
{"learn":[18.51947597],"iteration":309,"passed_time":0.04639506893,"remaining_time":0.09383776845},
{"learn":[18.50726403],"iteration":310,"passed_time":0.04651635671,"remaining_time":0.09363099454},
{"learn":[18.49487497],"iteration":311,"passed_time":0.04663781149,"remaining_time":0.09342510314},
{"learn":[18.48253713],"iteration":312,"passed_time":0.04674001778,"remaining_time":0.09318137729},
{"learn":[18.47043234],"iteration":313,"passed_time":0.04683101536,"remaining_time":0.09291631392},
{"learn":[18.45869443],"iteration":314,"passed_time":0.04693601258,"remaining_time":0.09267999943},
{"learn":[18.44541899],"iteration":315,"passed_time":0.0470518845,"remaining_time":0.09246588695},
{"learn":[18.43283201],"iteration":316,"passed_time":0.0472176301,"remaining_time":0.092349939},
{"learn":[18.42158855],"iteration":317,"passed_time":0.04732425227,"remaining_time":0.09211859169},
{"learn":[18.40944807],"iteration":318,"passed_time":0.04740929202,"remaining_time":0.09184621463},
{"learn":[18.39716092],"iteration":319,"passed_time":0.04753478869,"remaining_time":0.09165301444},
{"learn":[18.38423256],"iteration":320,"passed_time":0.04762561928,"remaining_time":0.09139371176},
{"learn":[18.37117158],"iteration":321,"passed_time":0.04770845108,"remaining_time":0.0911201783},
{"learn":[18.35992142],"iteration":322,"passed_time":0.04780961539,"remaining_time":0.09088267447},
{"learn":[18.34762017],"iteration":323,"passed_time":0.04790582084,"remaining_time":0.09063663017},
{"learn":[18.33503154],"iteration":324,"passed_time":0.04801506794,"remaining_time":0.0904160664},
{"learn":[18.32409447],"iteration":325,"passed_time":0.04813564774,"remaining_time":0.09021742568},
{"learn":[18.31247104],"iteration":326,"passed_time":0.04826360235,"remaining_time":0.09003301967},
{"learn":[18.30095081],"iteration":327,"passed_time":0.04839005699,"remaining_time":0.08984617289},
{"learn":[18.2895102],"iteration":328,"passed_time":0.04848530447,"remaining_time":0.08960202163},
{"learn":[18.27803991],"iteration":329,"passed_time":0.04857359412,"remaining_time":0.08934597464},
{"learn":[18.26616572],"iteration":330,"passed_time":0.04868246623,"remaining_time":0.08912862398},
{"learn":[18.25454986],"iteration":331,"passed_time":0.04876338009,"remaining_time":0.08886097877},
{"learn":[18.24354387],"iteration":332,"passed_time":0.04886658535,"remaining_time":0.08863488754},
{"learn":[18.23215191],"iteration":333,"passed_time":0.048955124,"remaining_time":0.08838305321},
{"learn":[18.22122879],"iteration":334,"passed_time":0.04906237115,"remaining_time":0.08816581324},
{"learn":[18.20977273],"iteration":335,"passed_time":0.04919528363,"remaining_time":0.0879951353},
{"learn":[18.19828868],"iteration":336,"passed_time":0.04931565543,"remaining_time":0.08780235389},
{"learn":[18.18782649],"iteration":337,"passed_time":0.049445027,"remaining_time":0.08762595022},
{"learn":[18.17679532],"iteration":338,"passed_time":0.0495466903,"remaining_time":0.08740094631},
{"learn":[18.16539327],"iteration":339,"passed_time":0.04967810382,"remaining_time":0.08722890582},
{"learn":[18.15295462],"iteration":340,"passed_time":0.04976664347,"remaining_time":0.08698216864},
{"learn":[18.14135762],"iteration":341,"passed_time":0.04986651582,"remaining_time":0.08675607284},
{"learn":[18.13100547],"iteration":342,"passed_time":0.0499990963,"remaining_time":0.08658735627},
{"learn":[18.12043214],"iteration":343,"passed_time":0.0501573011,"remaining_time":0.08646302195},
{"learn":[18.10940258],"iteration":344,"passed_time":0.05024700672,"remaining_time":0.08622095066},
{"learn":[18.09852434],"iteration":345,"passed_time":0.0503609207,"remaining_time":0.08602111021},
{"learn":[18.08651885],"iteration":346,"passed_time":0.05047179275,"remaining_time":0.08581659287},
{"learn":[18.07510045],"iteration":347,"passed_time":0.05058074786,"remaining_time":0.08560936923},
{"learn":[18.06485588],"iteration":348,"passed_time":0.05069199491,"remaining_time":0.08540657022},
{"learn":[18.05360914],"iteration":349,"passed_time":0.05082032551,"remaining_time":0.08523294592},
{"learn":[18.04241552],"iteration":350,"passed_time":0.05091457301,"remaining_time":0.08500267744},
{"learn":[18.03146958],"iteration":351,"passed_time":0.05102444509,"remaining_time":0.0847991488},
{"learn":[18.02090701],"iteration":352,"passed_time":0.05111990056,"remaining_time":0.08457230007},
{"learn":[18.00975606],"iteration":353,"passed_time":0.05128560516,"remaining_time":0.08446188647},
{"learn":[17.9987585],"iteration":354,"passed_time":0.0514235595,"remaining_time":0.08430566656},
{"learn":[17.98778266],"iteration":355,"passed_time":0.05151572305,"remaining_time":0.08407481768},
{"learn":[17.97820726],"iteration":356,"passed_time":0.05163780382,"remaining_time":0.08389335074},
{"learn":[17.96754496],"iteration":357,"passed_time":0.05173692619,"remaining_time":0.08367508453},
{"learn":[17.95653075],"iteration":358,"passed_time":0.05188150535,"remaining_time":0.08353066878},
{"learn":[17.94554293],"iteration":359,"passed_time":0.05197604484,"remaining_time":0.08330604965},
{"learn":[17.93522879],"iteration":360,"passed_time":0.05210608339,"remaining_time":0.08313879233},
{"learn":[17.92556854],"iteration":361,"passed_time":0.05220799669,"remaining_time":0.08292706656},
{"learn":[17.91518809],"iteration":362,"passed_time":0.05229591135,"remaining_time":0.08269381024},
{"learn":[17.90448767],"iteration":363,"passed_time":0.0524449494,"remaining_time":0.08255757144},
{"learn":[17.89383418],"iteration":364,"passed_time":0.05255902937,"remaining_time":0.0823664789},
{"learn":[17.88538219],"iteration":365,"passed_time":0.05266140165,"remaining_time":0.08215754193},
{"learn":[17.87497881],"iteration":366,"passed_time":0.05277752357,"remaining_time":0.0819705407},
{"learn":[17.86639114],"iteration":367,"passed_time":0.0528518546,"remaining_time":0.08171930779},
{"learn":[17.85641529],"iteration":368,"passed_time":0.05292506066,"remaining_time":0.08146730204},
{"learn":[17.84705954],"iteration":369,"passed_time":0.05301443329,"remaining_time":0.08124103696},
{"learn":[17.83651895],"iteration":370,"passed_time":0.05311409764,"remaining_time":0.08103121096},
{"learn":[17.8272374],"iteration":371,"passed_time":0.0532023453,"remaining_time":0.08080463735},
{"learn":[17.81666517],"iteration":372,"passed_time":0.05332946693,"remaining_time":0.08063758538},
{"learn":[17.80756831],"iteration":373,"passed_time":0.0534360051,"remaining_time":0.08043976169},
{"learn":[17.79737604],"iteration":374,"passed_time":0.0535414603,"remaining_time":0.08024080184},
{"learn":[17.78593336],"iteration":375,"passed_time":0.05376087148,"remaining_time":0.0802123641},
{"learn":[17.7768105],"iteration":376,"passed_time":0.0538768264,"remaining_time":0.08002923816},
{"learn":[17.76635815],"iteration":377,"passed_time":0.05399928115,"remaining_time":0.0798560798},
{"learn":[17.75502243],"iteration":378,"passed_time":0.05411636105,"remaining_time":0.07967527563},
{"learn":[17.74501436],"iteration":379,"passed_time":0.05421015056,"remaining_time":0.07946066806},
{"learn":[17.73464877],"iteration":380,"passed_time":0.05430706399,"remaining_time":0.07925125348},
{"learn":[17.7243578],"iteration":381,"passed_time":0.05441806104,"remaining_time":0.07906288973},
{"learn":[17.71453537],"iteration":382,"passed_time":0.05451185055,"remaining_time":0.0788500397},
{"learn":[17.70532199],"iteration":383,"passed_time":0.05461422284,"remaining_time":0.07865016987},
{"learn":[17.69625839],"iteration":384,"passed_time":0.05475838601,"remaining_time":0.07851072488},
{"learn":[17.68662055],"iteration":385,"passed_time":0.05490171521,"remaining_time":0.07837006497},
{"learn":[17.678057],"iteration":386,"passed_time":0.05501025433,"remaining_time":0.07817994801},
{"learn":[17.66926613],"iteration":387,"passed_time":0.05509271114,"remaining_time":0.07795334643},
{"learn":[17.65919683],"iteration":388,"passed_time":0.05518995856,"remaining_time":0.07774832209},
{"learn":[17.65047525],"iteration":389,"passed_time":0.05529866368,"remaining_time":0.07755992059},
{"learn":[17.64086474],"iteration":390,"passed_time":0.0554335771,"remaining_time":0.07740852454},
{"learn":[17.63024725],"iteration":391,"passed_time":0.05554674109,"remaining_time":0.07722697422},
{"learn":[17.62054333],"iteration":392,"passed_time":0.05564519648,"remaining_time":0.07702541192},
{"learn":[17.61163151],"iteration":393,"passed_time":0.05577923492,"remaining_time":0.0768734126},
{"learn":[17.60197559],"iteration":394,"passed_time":0.05591044044,"remaining_time":0.07671761701},
{"learn":[17.59150035],"iteration":395,"passed_time":0.05601327171,"remaining_time":0.07652318181},
{"learn":[17.58170402],"iteration":396,"passed_time":0.0561004364,"remaining_time":0.07630789838},
{"learn":[17.5721528],"iteration":397,"passed_time":0.0562060996,"remaining_time":0.07611831076},
{"learn":[17.56250086],"iteration":398,"passed_time":0.05631242978,"remaining_time":0.07593004316},
{"learn":[17.55409126],"iteration":399,"passed_time":0.05644263432,"remaining_time":0.07577423658},
{"learn":[17.54571884],"iteration":400,"passed_time":0.05657396384,"remaining_time":0.07562006139},
{"learn":[17.53777982],"iteration":401,"passed_time":0.05669466863,"remaining_time":0.07545186},
{"learn":[17.52856103],"iteration":402,"passed_time":0.05681574842,"remaining_time":0.07528439121},
{"learn":[17.51906915],"iteration":403,"passed_time":0.05696620243,"remaining_time":0.07515590568},
{"learn":[17.51038387],"iteration":404,"passed_time":0.05708965715,"remaining_time":0.07499184594},
{"learn":[17.50127627],"iteration":405,"passed_time":0.05720161318,"remaining_time":0.07481294729},
{"learn":[17.49282038],"iteration":406,"passed_time":0.05734273444,"remaining_time":0.07467235688},
{"learn":[17.48331002],"iteration":407,"passed_time":0.05746710614,"remaining_time":0.07451004693},
{"learn":[17.47394143],"iteration":408,"passed_time":0.05759431176,"remaining_time":0.07435158095},
{"learn":[17.4645194],"iteration":409,"passed_time":0.05768389339,"remaining_time":0.07414490686},
{"learn":[17.45521254],"iteration":410,"passed_time":0.05777539096,"remaining_time":0.07394125461},
{"learn":[17.44629615],"iteration":411,"passed_time":0.05791380428,"remaining_time":0.07379793022},
{"learn":[17.43723911],"iteration":412,"passed_time":0.0580336761,"remaining_time":0.07363110479},
{"learn":[17.42924996],"iteration":413,"passed_time":0.05813292347,"remaining_time":0.07343845163},
{"learn":[17.42037645],"iteration":414,"passed_time":0.05823300381,"remaining_time":0.07324729636},
{"learn":[17.41244362],"iteration":415,"passed_time":0.05831525163,"remaining_time":0.07303424543},
{"learn":[17.40408533],"iteration":416,"passed_time":0.05852349611,"remaining_time":0.07297893999},
{"learn":[17.39498615],"iteration":417,"passed_time":0.05861065979,"remaining_time":0.07277256563},
{"learn":[17.38592639],"iteration":418,"passed_time":0.05870865719,"remaining_time":0.07258015376},
{"learn":[17.37710456],"iteration":419,"passed_time":0.05883302889,"remaining_time":0.07242065699},
{"learn":[17.3678064],"iteration":420,"passed_time":0.05896594137,"remaining_time":0.07227179512},
{"learn":[17.35804753],"iteration":421,"passed_time":0.05905993887,"remaining_time":0.07207551782},
{"learn":[17.34908614],"iteration":422,"passed_time":0.05914381165,"remaining_time":0.07186742124},
{"learn":[17.34059401],"iteration":423,"passed_time":0.059243434,"remaining_time":0.07167896614},
{"learn":[17.33289933],"iteration":424,"passed_time":0.05933318162,"remaining_time":0.07147903292},
{"learn":[17.32326921],"iteration":425,"passed_time":0.0594281791,"remaining_time":0.07128591437},
{"learn":[17.31552825],"iteration":426,"passed_time":0.05953605124,"remaining_time":0.07110863263},
{"learn":[17.30755849],"iteration":427,"passed_time":0.05964417337,"remaining_time":0.07093197254},
{"learn":[17.29920376],"iteration":428,"passed_time":0.05976421218,"remaining_time":0.0707697431},
{"learn":[17.29013498],"iteration":429,"passed_time":0.05985887667,"remaining_time":0.0705777918},
{"learn":[17.2820538],"iteration":430,"passed_time":0.0599634159,"remaining_time":0.07039788502},
{"learn":[17.27459441],"iteration":431,"passed_time":0.06009345445,"remaining_time":0.07024813541},
{"learn":[17.26600542],"iteration":432,"passed_time":0.06018832693,"remaining_time":0.07005754451},
{"learn":[17.25692769],"iteration":433,"passed_time":0.06029774003,"remaining_time":0.06988424708},
{"learn":[17.25072069],"iteration":434,"passed_time":0.06041507091,"remaining_time":0.06972038069},
{"learn":[17.24255095],"iteration":435,"passed_time":0.06053585971,"remaining_time":0.06956070118},
{"learn":[17.23404079],"iteration":436,"passed_time":0.06062081646,"remaining_time":0.06936020189},
{"learn":[17.22667304],"iteration":437,"passed_time":0.06070689717,"remaining_time":0.0691615107},
{"learn":[17.21675396],"iteration":438,"passed_time":0.06079931172,"remaining_time":0.06897051762},
{"learn":[17.20813443],"iteration":439,"passed_time":0.06089205926,"remaining_time":0.06878034875},
{"learn":[17.20023853],"iteration":440,"passed_time":0.06099801445,"remaining_time":0.06860547657},
{"learn":[17.19298236],"iteration":441,"passed_time":0.06112813599,"remaining_time":0.06845798036},
{"learn":[17.1844565],"iteration":442,"passed_time":0.06122405045,"remaining_time":0.06827241743},
{"learn":[17.17559934],"iteration":443,"passed_time":0.06134179732,"remaining_time":0.06811150018},
{"learn":[17.16728832],"iteration":444,"passed_time":0.0614785017,"remaining_time":0.06797173671},
{"learn":[17.15948297],"iteration":445,"passed_time":0.0615765401,"remaining_time":0.0677894197},
{"learn":[17.1523576],"iteration":446,"passed_time":0.06166545474,"remaining_time":0.06759747835},
{"learn":[17.14380102],"iteration":447,"passed_time":0.06175970224,"remaining_time":0.06741181784},
{"learn":[17.13614141],"iteration":448,"passed_time":0.06184349101,"remaining_time":0.06721519736},
{"learn":[17.12777141],"iteration":449,"passed_time":0.061919239,"remaining_time":0.06701037643},
{"learn":[17.11944078],"iteration":450,"passed_time":0.06203040305,"remaining_time":0.06684429242},
{"learn":[17.11102229],"iteration":451,"passed_time":0.06214810793,"remaining_time":0.06668546979},
{"learn":[17.10301002],"iteration":452,"passed_time":0.06243126742,"remaining_time":0.0667036058},
{"learn":[17.09475],"iteration":453,"passed_time":0.06251980707,"remaining_time":0.06651336302},
{"learn":[17.08729685],"iteration":454,"passed_time":0.06261738748,"remaining_time":0.06633314454},
{"learn":[17.07772979],"iteration":455,"passed_time":0.06271525988,"remaining_time":0.0661535965},
{"learn":[17.06981593],"iteration":456,"passed_time":0.0628162982,"remaining_time":0.06597773115},
{"learn":[17.06154075],"iteration":457,"passed_time":0.06293475406,"remaining_time":0.06582040872},
{"learn":[17.05354009],"iteration":458,"passed_time":0.06307466734,"remaining_time":0.06568560129},
{"learn":[17.04468495],"iteration":459,"passed_time":0.06320195597,"remaining_time":0.06553768043},
{"learn":[17.0366141],"iteration":460,"passed_time":0.06328716171,"remaining_time":0.0653463969},
{"learn":[17.03003063],"iteration":461,"passed_time":0.06355686255,"remaining_time":0.06534525911},
{"learn":[17.02251054],"iteration":462,"passed_time":0.06367669237,"remaining_time":0.06518952955},
{"learn":[17.01456297],"iteration":463,"passed_time":0.06379481423,"remaining_time":0.06503221365},
{"learn":[17.00771458],"iteration":464,"passed_time":0.06393256058,"remaining_time":0.06489498622},
{"learn":[16.99929905],"iteration":465,"passed_time":0.0640710979,"remaining_time":0.06475855604},
{"learn":[16.99280924],"iteration":466,"passed_time":0.06419480362,"remaining_time":0.06460718994},
{"learn":[16.98500585],"iteration":467,"passed_time":0.06428317628,"remaining_time":0.06442053349},
{"learn":[16.9763476],"iteration":468,"passed_time":0.06439846422,"remaining_time":0.06426115406},
{"learn":[16.96867497],"iteration":469,"passed_time":0.06448533691,"remaining_time":0.06407372838},
{"learn":[16.96067692],"iteration":470,"passed_time":0.06458095937,"remaining_time":0.06389538656},
{"learn":[16.95352376],"iteration":471,"passed_time":0.06469649831,"remaining_time":0.06373701634},
{"learn":[16.94599076],"iteration":472,"passed_time":0.0648135362,"remaining_time":0.06358029767},
{"learn":[16.93806499],"iteration":473,"passed_time":0.06496019831,"remaining_time":0.06345268316},
{"learn":[16.93139685],"iteration":474,"passed_time":0.065084987,"remaining_time":0.06330371367},
{"learn":[16.92414841],"iteration":475,"passed_time":0.06519323413,"remaining_time":0.06313882549},
{"learn":[16.91642349],"iteration":476,"passed_time":0.06532706358,"remaining_time":0.06299884538},
{"learn":[16.90866653],"iteration":477,"passed_time":0.06545501818,"remaining_time":0.06285324968},
{"learn":[16.90090161],"iteration":478,"passed_time":0.0655411409,"remaining_time":0.06266772971},
{"learn":[16.89340624],"iteration":479,"passed_time":0.0656654286,"remaining_time":0.06251896015},
{"learn":[16.88596328],"iteration":480,"passed_time":0.06576442597,"remaining_time":0.06234631651},
{"learn":[16.8781754],"iteration":481,"passed_time":0.06589283956,"remaining_time":0.06220174689},
{"learn":[16.87042381],"iteration":482,"passed_time":0.06600521158,"remaining_time":0.06204216575},
{"learn":[16.86285482],"iteration":483,"passed_time":0.06610529193,"remaining_time":0.0618712753},
{"learn":[16.85570876],"iteration":484,"passed_time":0.06620320633,"remaining_time":0.06169865827},
{"learn":[16.84672626],"iteration":485,"passed_time":0.06629570387,"remaining_time":0.06152132191},
{"learn":[16.84039241],"iteration":486,"passed_time":0.06642011757,"remaining_time":0.06137382527},
{"learn":[16.8321718],"iteration":487,"passed_time":0.06653886442,"remaining_time":0.06122120927},
{"learn":[16.82557837],"iteration":488,"passed_time":0.06662427816,"remaining_time":0.06103819348},
{"learn":[16.81741723],"iteration":489,"passed_time":0.06673323327,"remaining_time":0.06087705157},
{"learn":[16.81121939],"iteration":490,"passed_time":0.06681977297,"remaining_time":0.06069576119},
{"learn":[16.80407267],"iteration":491,"passed_time":0.06698489359,"remaining_time":0.06058593018},
{"learn":[16.79762527],"iteration":492,"passed_time":0.06712322392,"remaining_time":0.0604517473},
{"learn":[16.79006122],"iteration":493,"passed_time":0.0672480956,"remaining_time":0.06030547845},
{"learn":[16.78356093],"iteration":494,"passed_time":0.06735217584,"remaining_time":0.06014073075},
{"learn":[16.77572478],"iteration":495,"passed_time":0.06746646481,"remaining_time":0.0599853044},
{"learn":[16.76906669],"iteration":496,"passed_time":0.06758916955,"remaining_time":0.05983749417},
{"learn":[16.76178844],"iteration":497,"passed_time":0.06772145804,"remaining_time":0.05969823309},
{"learn":[16.75538511],"iteration":498,"passed_time":0.06781791448,"remaining_time":0.05952754818},
{"learn":[16.7479478],"iteration":499,"passed_time":0.0679189958,"remaining_time":0.05936120233},
{"learn":[16.74096984],"iteration":500,"passed_time":0.06802753392,"remaining_time":0.05920160637},
{"learn":[16.73378412],"iteration":501,"passed_time":0.06819819639,"remaining_time":0.05909604668},
{"learn":[16.72752127],"iteration":502,"passed_time":0.06833110987,"remaining_time":0.05895765742},
{"learn":[16.72101875],"iteration":503,"passed_time":0.06846460632,"remaining_time":0.05881979075},
{"learn":[16.71480417],"iteration":504,"passed_time":0.06862264313,"remaining_time":0.05870293432},
{"learn":[16.70771363],"iteration":505,"passed_time":0.06874755682,"remaining_time":0.05855770156},
{"learn":[16.70155404],"iteration":506,"passed_time":0.06885901286,"remaining_time":0.05840113517},
{"learn":[16.69426333],"iteration":507,"passed_time":0.06896042717,"remaining_time":0.05823626625},
{"learn":[16.6866473],"iteration":508,"passed_time":0.06905588363,"remaining_time":0.05806663693},
{"learn":[16.67946725],"iteration":509,"passed_time":0.06918567219,"remaining_time":0.05792604319},
{"learn":[16.67264819],"iteration":510,"passed_time":0.06931162685,"remaining_time":0.05778229557},
{"learn":[16.66543524],"iteration":511,"passed_time":0.06940116647,"remaining_time":0.05760839014},
{"learn":[16.6587894],"iteration":512,"passed_time":0.06955745433,"remaining_time":0.05748998174},
{"learn":[16.65140907],"iteration":513,"passed_time":0.06970340945,"remaining_time":0.05736292257},
{"learn":[16.64296205],"iteration":514,"passed_time":0.06980753169,"remaining_time":0.0572015114},
{"learn":[16.6358113],"iteration":515,"passed_time":0.06993577829,"remaining_time":0.05706000515},
{"learn":[16.62980763],"iteration":516,"passed_time":0.07004590037,"remaining_time":0.05690382622},
{"learn":[16.62350602],"iteration":517,"passed_time":0.07017872984,"remaining_time":0.05676619267},
{"learn":[16.61588933],"iteration":518,"passed_time":0.07029085187,"remaining_time":0.05661189996},
{"learn":[16.60830915],"iteration":519,"passed_time":0.07046313929,"remaining_time":0.05650601747},
{"learn":[16.60214859],"iteration":520,"passed_time":0.07068550839,"remaining_time":0.05643986851},
{"learn":[16.59552152],"iteration":521,"passed_time":0.07083271249,"remaining_time":0.05631336338},
{"learn":[16.58940077],"iteration":522,"passed_time":0.07093137587,"remaining_time":0.05614835489},
{"learn":[16.58244714],"iteration":523,"passed_time":0.07106995519,"remaining_time":0.0560150601},
{"learn":[16.57582466],"iteration":524,"passed_time":0.07119486788,"remaining_time":0.05587102013},
{"learn":[16.56877035],"iteration":525,"passed_time":0.07133394719,"remaining_time":0.05573812223},
{"learn":[16.56271212],"iteration":526,"passed_time":0.07144448625,"remaining_time":0.0555829969},
{"learn":[16.55680006],"iteration":527,"passed_time":0.07154869149,"remaining_time":0.05542313413},
{"learn":[16.55198837],"iteration":528,"passed_time":0.07164839684,"remaining_time":0.05526001118},
{"learn":[16.54511122],"iteration":529,"passed_time":0.07175239408,"remaining_time":0.05510042338},
{"learn":[16.53814031],"iteration":530,"passed_time":0.07183547488,"remaining_time":0.05492505236},
{"learn":[16.53215383],"iteration":531,"passed_time":0.07192451352,"remaining_time":0.05475456386},
{"learn":[16.52656077],"iteration":532,"passed_time":0.07201617808,"remaining_time":0.05458637138},
{"learn":[16.51977557],"iteration":533,"passed_time":0.07214529966,"remaining_time":0.05444673364},
{"learn":[16.51251428],"iteration":534,"passed_time":0.07223504728,"remaining_time":0.05427754954},
{"learn":[16.50574882],"iteration":535,"passed_time":0.07233471163,"remaining_time":0.0541160809},
{"learn":[16.49970357],"iteration":536,"passed_time":0.07244212478,"remaining_time":0.05396061436},
{"learn":[16.49290255],"iteration":537,"passed_time":0.07258874589,"remaining_time":0.05383440448},
{"learn":[16.48820582],"iteration":538,"passed_time":0.07271782647,"remaining_time":0.05369516685},
{"learn":[16.48352681],"iteration":539,"passed_time":0.07283903125,"remaining_time":0.05355017668},
{"learn":[16.47805517],"iteration":540,"passed_time":0.07300473485,"remaining_time":0.05343784658},
{"learn":[16.4721861],"iteration":541,"passed_time":0.07313352344,"remaining_time":0.05329841653},
{"learn":[16.46633253],"iteration":542,"passed_time":0.07328347746,"remaining_time":0.05317438327},
{"learn":[16.4602939],"iteration":543,"passed_time":0.07341643293,"remaining_time":0.05303797452},
{"learn":[16.45445252],"iteration":544,"passed_time":0.07351580529,"remaining_time":0.05287742326},
{"learn":[16.44805844],"iteration":545,"passed_time":0.07362176148,"remaining_time":0.05272181088},
{"learn":[16.44148514],"iteration":546,"passed_time":0.07373509147,"remaining_time":0.05257163743},
{"learn":[16.43493903],"iteration":547,"passed_time":0.07385771322,"remaining_time":0.05242819424},
{"learn":[16.42845274],"iteration":548,"passed_time":0.07397508511,"remaining_time":0.05228111661},
{"learn":[16.42184001],"iteration":549,"passed_time":0.07407783238,"remaining_time":0.0521238566},
{"learn":[16.41539705],"iteration":550,"passed_time":0.07419107937,"remaining_time":0.05197414998},
{"learn":[16.40968234],"iteration":551,"passed_time":0.07430099246,"remaining_time":0.05182225017},
{"learn":[16.40417131],"iteration":552,"passed_time":0.07441815535,"remaining_time":0.05167553645},
{"learn":[16.39809189],"iteration":553,"passed_time":0.07453256931,"remaining_time":0.05152702897},
{"learn":[16.39229593],"iteration":554,"passed_time":0.07462227593,"remaining_time":0.05136163857},
{"learn":[16.38570835],"iteration":555,"passed_time":0.07473606391,"remaining_time":0.05121302221},
{"learn":[16.38046884],"iteration":556,"passed_time":0.07482006169,"remaining_time":0.05104420725},
{"learn":[16.37352688],"iteration":557,"passed_time":0.07491989204,"remaining_time":0.05088644997},
{"learn":[16.3666673],"iteration":558,"passed_time":0.07502634821,"remaining_time":0.05073338036},
{"learn":[16.35973601],"iteration":559,"passed_time":0.07515692775,"remaining_time":0.05059671743},
{"learn":[16.35280483],"iteration":560,"passed_time":0.07525688409,"remaining_time":0.05043955155},
{"learn":[16.34630599],"iteration":561,"passed_time":0.07537617293,"remaining_time":0.05029548905},
{"learn":[16.34187413],"iteration":562,"passed_time":0.07550383654,"remaining_time":0.05015707792},
{"learn":[16.33598127],"iteration":563,"passed_time":0.07563583304,"remaining_time":0.05002157043},
{"learn":[16.33016322],"iteration":564,"passed_time":0.07574995501,"remaining_time":0.04987430666},
{"learn":[16.32484408],"iteration":565,"passed_time":0.07587599267,"remaining_time":0.04973497046},
{"learn":[16.31933498],"iteration":566,"passed_time":0.07603465446,"remaining_time":0.04961697028},
{"learn":[16.31380559],"iteration":567,"passed_time":0.07616606797,"remaining_time":0.04948112514},
{"learn":[16.30755774],"iteration":568,"passed_time":0.07628485682,"remaining_time":0.0493371306},
{"learn":[16.30133885],"iteration":569,"passed_time":0.07638956204,"remaining_time":0.04918415661},
{"learn":[16.29455775],"iteration":570,"passed_time":0.07651626668,"remaining_time":0.0490454529},
{"learn":[16.29023923],"iteration":571,"passed_time":0.07661880596,"remaining_time":0.04889137093},
{"learn":[16.28351218],"iteration":572,"passed_time":0.07670409569,"remaining_time":0.04872651105},
{"learn":[16.2777096],"iteration":573,"passed_time":0.0767829266,"remaining_time":0.04855784383},
{"learn":[16.27176887],"iteration":574,"passed_time":0.07693688052,"remaining_time":0.04843678391},
{"learn":[16.26510288],"iteration":575,"passed_time":0.07703879481,"remaining_time":0.04828299467},
{"learn":[16.25881544],"iteration":576,"passed_time":0.07714158408,"remaining_time":0.04812993114},
{"learn":[16.25342598],"iteration":577,"passed_time":0.07723053972,"remaining_time":0.04796844941},
{"learn":[16.24738702],"iteration":578,"passed_time":0.07734145278,"remaining_time":0.04782079464},
{"learn":[16.24240888],"iteration":579,"passed_time":0.07746019963,"remaining_time":0.04767808839},
{"learn":[16.23635981],"iteration":580,"passed_time":0.07757682154,"remaining_time":0.04753416259},
{"learn":[16.22999502],"iteration":581,"passed_time":0.07772669256,"remaining_time":0.04741061144},
{"learn":[16.2245864],"iteration":582,"passed_time":0.07792981217,"remaining_time":0.04731930276},
{"learn":[16.21916261],"iteration":583,"passed_time":0.07805060096,"remaining_time":0.04717784613},
{"learn":[16.21260709],"iteration":584,"passed_time":0.07813922361,"remaining_time":0.04701710549},
{"learn":[16.20722891],"iteration":585,"passed_time":0.07823747101,"remaining_time":0.04686237598},
{"learn":[16.20126443],"iteration":586,"passed_time":0.07848475644,"remaining_time":0.04679670316},
{"learn":[16.19711941],"iteration":587,"passed_time":0.07862562771,"remaining_time":0.04666725182},
{"learn":[16.19153241],"iteration":588,"passed_time":0.07876749894,"remaining_time":0.04653835252},
{"learn":[16.18620073],"iteration":589,"passed_time":0.07890870419,"remaining_time":0.04640901755},
{"learn":[16.1800891],"iteration":590,"passed_time":0.0790404087,"remaining_time":0.04627408022},
{"learn":[16.17362583],"iteration":591,"passed_time":0.07914928081,"remaining_time":0.04612584777},
{"learn":[16.16775741],"iteration":592,"passed_time":0.07926161083,"remaining_time":0.04597975401},
{"learn":[16.1622927],"iteration":593,"passed_time":0.07936881599,"remaining_time":0.04583081462},
{"learn":[16.15646623],"iteration":594,"passed_time":0.07946102154,"remaining_time":0.04567339389},
{"learn":[16.15166571],"iteration":595,"passed_time":0.07961297551,"remaining_time":0.04555037693},
{"learn":[16.14644238],"iteration":596,"passed_time":0.07972138963,"remaining_time":0.04540246646},
{"learn":[16.1416879],"iteration":597,"passed_time":0.07982392891,"remaining_time":0.04525135769},
{"learn":[16.13695423],"iteration":598,"passed_time":0.07995684138,"remaining_time":0.0451175499},
{"learn":[16.13120242],"iteration":599,"passed_time":0.08010983732,"remaining_time":0.0449950253},
{"learn":[16.1254568],"iteration":600,"passed_time":0.0802314591,"remaining_time":0.044854859},
{"learn":[16.11999889],"iteration":601,"passed_time":0.08037653925,"remaining_time":0.04472780838},
{"learn":[16.11456645],"iteration":602,"passed_time":0.08049670306,"remaining_time":0.04458689688},
{"learn":[16.1088789],"iteration":603,"passed_time":0.08064253219,"remaining_time":0.044460204},
{"learn":[16.10400845],"iteration":604,"passed_time":0.0807477794,"remaining_time":0.04431117811},
{"learn":[16.09861967],"iteration":605,"passed_time":0.0808796919,"remaining_time":0.04417686141},
{"learn":[16.09377616],"iteration":606,"passed_time":0.08100206365,"remaining_time":0.04403736574},
{"learn":[16.08980996],"iteration":607,"passed_time":0.0811056029,"remaining_time":0.04388773578},
{"learn":[16.08418918],"iteration":608,"passed_time":0.08123964134,"remaining_time":0.04375468368},
{"learn":[16.07778943],"iteration":609,"passed_time":0.08134659751,"remaining_time":0.04360711047},
{"learn":[16.07319484],"iteration":610,"passed_time":0.08148092794,"remaining_time":0.04347427579},
{"learn":[16.06787723],"iteration":611,"passed_time":0.08158150827,"remaining_time":0.04332351338},
{"learn":[16.06299354],"iteration":612,"passed_time":0.08169754619,"remaining_time":0.04318108477},
{"learn":[16.05684051],"iteration":613,"passed_time":0.08180762627,"remaining_time":0.04303560796},
{"learn":[16.05050123],"iteration":614,"passed_time":0.08191162351,"remaining_time":0.04288706142},
{"learn":[16.04596928],"iteration":615,"passed_time":0.08200553802,"remaining_time":0.04273340537},
{"learn":[16.04016259],"iteration":616,"passed_time":0.08209361868,"remaining_time":0.04257691731},
{"learn":[16.03566295],"iteration":617,"passed_time":0.0822247812,"remaining_time":0.04244288868},
{"learn":[16.03178118],"iteration":618,"passed_time":0.08237286028,"remaining_time":0.04231755988},
{"learn":[16.02594704],"iteration":619,"passed_time":0.08247398259,"remaining_time":0.04216814916},
{"learn":[16.02047963],"iteration":620,"passed_time":0.08256981305,"remaining_time":0.04201620117},
{"learn":[16.01663731],"iteration":621,"passed_time":0.08284234782,"remaining_time":0.04195392213},
{"learn":[16.01178431],"iteration":622,"passed_time":0.08293934524,"remaining_time":0.04180249503},
{"learn":[16.00726718],"iteration":623,"passed_time":0.08303684266,"remaining_time":0.04165149319},
{"learn":[16.00117971],"iteration":624,"passed_time":0.08313379908,"remaining_time":0.0415003925},
{"learn":[15.99595893],"iteration":625,"passed_time":0.08323779632,"remaining_time":0.04135296271},
{"learn":[15.990463],"iteration":626,"passed_time":0.08337091779,"remaining_time":0.041220071},
{"learn":[15.9854064],"iteration":627,"passed_time":0.0834610814,"remaining_time":0.04106604164},
{"learn":[15.98007163],"iteration":628,"passed_time":0.08358499511,"remaining_time":0.04092874164},
{"learn":[15.97476171],"iteration":629,"passed_time":0.08371690861,"remaining_time":0.04079538245},
{"learn":[15.96998202],"iteration":630,"passed_time":0.08384648817,"remaining_time":0.04066089601},
{"learn":[15.96517523],"iteration":631,"passed_time":0.0839773187,"remaining_time":0.0405270288},
{"learn":[15.96019646],"iteration":632,"passed_time":0.0840981075,"remaining_time":0.04038834862},
{"learn":[15.95462958],"iteration":633,"passed_time":0.08420652162,"remaining_time":0.04024381081},
{"learn":[15.94938415],"iteration":634,"passed_time":0.08432168456,"remaining_time":0.04010259644},
{"learn":[15.9438489],"iteration":635,"passed_time":0.08442618179,"remaining_time":0.03995641623},
{"learn":[15.93863755],"iteration":636,"passed_time":0.08452159626,"remaining_time":0.03980608929},
{"learn":[15.93434895],"iteration":637,"passed_time":0.08519537038,"remaining_time":0.03992698392},
{"learn":[15.92846541],"iteration":638,"passed_time":0.08534736635,"remaining_time":0.03980205817},
{"learn":[15.92350971],"iteration":639,"passed_time":0.08546173831,"remaining_time":0.03965958794},
{"learn":[15.91766798],"iteration":640,"passed_time":0.08558898494,"remaining_time":0.03952315061},
{"learn":[15.91213604],"iteration":641,"passed_time":0.08574210587,"remaining_time":0.0393986312},
{"learn":[15.9066184],"iteration":642,"passed_time":0.08585143597,"remaining_time":0.03925400027},
{"learn":[15.90295155],"iteration":643,"passed_time":0.08595801614,"remaining_time":0.03910822784},
{"learn":[15.89929836],"iteration":644,"passed_time":0.08605467958,"remaining_time":0.0389580875},
{"learn":[15.89374488],"iteration":645,"passed_time":0.08619163495,"remaining_time":0.0388262628},
{"learn":[15.88887486],"iteration":646,"passed_time":0.08631621464,"remaining_time":0.03868887519},
{"learn":[15.88363785],"iteration":647,"passed_time":0.08643192057,"remaining_time":0.03854756951},
{"learn":[15.87857608],"iteration":648,"passed_time":0.08654512557,"remaining_time":0.03840523292},
{"learn":[15.87482036],"iteration":649,"passed_time":0.08663770611,"remaining_time":0.03825387947},
{"learn":[15.86978751],"iteration":650,"passed_time":0.08675082811,"remaining_time":0.03811173094},
{"learn":[15.86620596],"iteration":651,"passed_time":0.0868565753,"remaining_time":0.03796644779},
{"learn":[15.8613545],"iteration":652,"passed_time":0.08696023955,"remaining_time":0.03782037984},
{"learn":[15.85778899],"iteration":653,"passed_time":0.08705319608,"remaining_time":0.03766980809},
{"learn":[15.85342015],"iteration":654,"passed_time":0.08719915121,"remaining_time":0.03754222999},
{"learn":[15.84860112],"iteration":655,"passed_time":0.08732948075,"remaining_time":0.03740790258},
{"learn":[15.84451785],"iteration":656,"passed_time":0.08742152031,"remaining_time":0.03725726893},
{"learn":[15.84098364],"iteration":657,"passed_time":0.08752897546,"remaining_time":0.03711334978},
{"learn":[15.83589106],"iteration":658,"passed_time":0.08766380588,"remaining_time":0.03698108958},
{"learn":[15.83021857],"iteration":659,"passed_time":0.0877875106,"remaining_time":0.03684415218},
{"learn":[15.82544606],"iteration":660,"passed_time":0.08791104932,"remaining_time":0.0367071855},
{"learn":[15.82072604],"iteration":661,"passed_time":0.08804229584,"remaining_time":0.03657346126},
{"learn":[15.81602807],"iteration":662,"passed_time":0.08818979193,"remaining_time":0.03644646001},
{"learn":[15.81114339],"iteration":663,"passed_time":0.08829145523,"remaining_time":0.03630055313},
{"learn":[15.80748917],"iteration":664,"passed_time":0.08840241028,"remaining_time":0.03615857985},
{"learn":[15.80287975],"iteration":665,"passed_time":0.08850649152,"remaining_time":0.03601390271},
{"learn":[15.79822873],"iteration":666,"passed_time":0.08861611361,"remaining_time":0.03587159022},
{"learn":[15.7947769],"iteration":667,"passed_time":0.08872148582,"remaining_time":0.0357276642},
{"learn":[15.79022916],"iteration":668,"passed_time":0.08882852498,"remaining_time":0.03558452122},
{"learn":[15.78498477],"iteration":669,"passed_time":0.08892789734,"remaining_time":0.03543843073},
{"learn":[15.78156018],"iteration":670,"passed_time":0.08901152012,"remaining_time":0.03528623599},
{"learn":[15.77634524],"iteration":671,"passed_time":0.08908968405,"remaining_time":0.03513209267},
{"learn":[15.77214087],"iteration":672,"passed_time":0.08919618122,"remaining_time":0.03498928951},
{"learn":[15.76761086],"iteration":673,"passed_time":0.08931267813,"remaining_time":0.03485049607},
{"learn":[15.76083161],"iteration":674,"passed_time":0.08942588313,"remaining_time":0.03471049093},
{"learn":[15.75666474],"iteration":675,"passed_time":0.08955242077,"remaining_time":0.03457571275},
{"learn":[15.7524091],"iteration":676,"passed_time":0.08966295884,"remaining_time":0.03443481432},
{"learn":[15.74810866],"iteration":677,"passed_time":0.08979574731,"remaining_time":0.03430250524},
{"learn":[15.74263322],"iteration":678,"passed_time":0.08992007701,"remaining_time":0.03416698066},
{"learn":[15.73817827],"iteration":679,"passed_time":0.09002519922,"remaining_time":0.03402422971},
{"learn":[15.73464867],"iteration":680,"passed_time":0.09013203039,"remaining_time":0.03388223169},
{"learn":[15.73113126],"iteration":681,"passed_time":0.09027019372,"remaining_time":0.03375205191},
{"learn":[15.727626],"iteration":682,"passed_time":0.09039998228,"remaining_time":0.03361873426},
{"learn":[15.72414103],"iteration":683,"passed_time":0.09057926952,"remaining_time":0.03350373566},
{"learn":[15.72027995],"iteration":684,"passed_time":0.0906968494,"remaining_time":0.03336584825},
{"learn":[15.71580221],"iteration":685,"passed_time":0.09083055385,"remaining_time":0.03323391985},
{"learn":[15.71164997],"iteration":686,"passed_time":0.09096921617,"remaining_time":0.03310379046},
{"learn":[15.70735793],"iteration":687,"passed_time":0.09110525457,"remaining_time":0.03297268661},
{"learn":[15.70287652],"iteration":688,"passed_time":0.09123533411,"remaining_time":0.0328394236},
{"learn":[15.69845968],"iteration":689,"passed_time":0.09135087305,"remaining_time":0.0327009647},
{"learn":[15.6942369],"iteration":690,"passed_time":0.09149307727,"remaining_time":0.03257206514},
{"learn":[15.68997985],"iteration":691,"passed_time":0.09163044863,"remaining_time":0.03244141606},
{"learn":[15.68671505],"iteration":692,"passed_time":0.09177436181,"remaining_time":0.03231305091},
{"learn":[15.68256849],"iteration":693,"passed_time":0.09190198342,"remaining_time":0.03217893656},
{"learn":[15.6781429],"iteration":694,"passed_time":0.09202139726,"remaining_time":0.03204198293},
{"learn":[15.67287236],"iteration":695,"passed_time":0.0921253945,"remaining_time":0.03189974149},
{"learn":[15.66875719],"iteration":696,"passed_time":0.09226330684,"remaining_time":0.03176928786},
{"learn":[15.66501245],"iteration":697,"passed_time":0.09237084598,"remaining_time":0.03162841288},
{"learn":[15.66178485],"iteration":698,"passed_time":0.09249438471,"remaining_time":0.03149308092},
{"learn":[15.6583963],"iteration":699,"passed_time":0.09260954765,"remaining_time":0.03135494685},
{"learn":[15.65518608],"iteration":700,"passed_time":0.09273287738,"remaining_time":0.03121962776},
{"learn":[15.65089446],"iteration":701,"passed_time":0.09285937402,"remaining_time":0.03108540298},
{"learn":[15.6475329],"iteration":702,"passed_time":0.09299724536,"remaining_time":0.03095498637},
{"learn":[15.64097379],"iteration":703,"passed_time":0.09312594995,"remaining_time":0.03082151468},
{"learn":[15.63671489],"iteration":704,"passed_time":0.09326494626,"remaining_time":0.03069144331},
{"learn":[15.6327489],"iteration":705,"passed_time":0.09339073492,"remaining_time":0.03055702517},
{"learn":[15.62940771],"iteration":706,"passed_time":0.09348914831,"remaining_time":0.03041372576},
{"learn":[15.62566547],"iteration":707,"passed_time":0.093613895,"remaining_time":0.03027907056},
{"learn":[15.62235022],"iteration":708,"passed_time":0.09385038872,"remaining_time":0.03018037888},
{"learn":[15.61786513],"iteration":709,"passed_time":0.09398067727,"remaining_time":0.0300473433},
{"learn":[15.61272982],"iteration":710,"passed_time":0.09411042382,"remaining_time":0.02991414316},
{"learn":[15.60761781],"iteration":711,"passed_time":0.09424604523,"remaining_time":0.02978280924},
{"learn":[15.60317162],"iteration":712,"passed_time":0.09435725127,"remaining_time":0.02964379283},
{"learn":[15.59944778],"iteration":713,"passed_time":0.09447249822,"remaining_time":0.02950611639},
{"learn":[15.5963328],"iteration":714,"passed_time":0.09475132482,"remaining_time":0.02941929246},
{"learn":[15.59162137],"iteration":715,"passed_time":0.09485265513,"remaining_time":0.02927714635},
{"learn":[15.58852663],"iteration":716,"passed_time":0.09505802468,"remaining_time":0.02916703686},
{"learn":[15.58525517],"iteration":717,"passed_time":0.09517252164,"remaining_time":0.02902894462},
{"learn":[15.58052364],"iteration":718,"passed_time":0.09531301791,"remaining_time":0.02889880098},
{"learn":[15.57614148],"iteration":719,"passed_time":0.09544751435,"remaining_time":0.0287668203},
{"learn":[15.57207833],"iteration":720,"passed_time":0.09558780262,"remaining_time":0.02863656778},
{"learn":[15.56745125],"iteration":721,"passed_time":0.09574384048,"remaining_time":0.02851097743},
{"learn":[15.56205568],"iteration":722,"passed_time":0.09590492021,"remaining_time":0.02838679519},
{"learn":[15.55565111],"iteration":723,"passed_time":0.09602479203,"remaining_time":0.02825038771},
{"learn":[15.55204423],"iteration":724,"passed_time":0.09616707925,"remaining_time":0.02812058042},
{"learn":[15.54840118],"iteration":725,"passed_time":0.09628049324,"remaining_time":0.02798234721},
{"learn":[15.54203362],"iteration":726,"passed_time":0.09637978261,"remaining_time":0.02784010227},
{"learn":[15.53797979],"iteration":727,"passed_time":0.09648394584,"remaining_time":0.02769937456},
{"learn":[15.53477816],"iteration":728,"passed_time":0.09665939919,"remaining_time":0.02757908783},
{"learn":[15.52844816],"iteration":729,"passed_time":0.09678131195,"remaining_time":0.02744346791},
{"learn":[15.52418469],"iteration":730,"passed_time":0.09686664269,"remaining_time":0.02729757646},
{"learn":[15.52100524],"iteration":731,"passed_time":0.09699459729,"remaining_time":0.02716378749},
{"learn":[15.51739314],"iteration":732,"passed_time":0.09712855174,"remaining_time":0.02703168425},
{"learn":[15.51339126],"iteration":733,"passed_time":0.09725171547,"remaining_time":0.02689659161},
{"learn":[15.50711184],"iteration":734,"passed_time":0.09738346198,"remaining_time":0.02676389023},
{"learn":[15.50221128],"iteration":735,"passed_time":0.09747741848,"remaining_time":0.02662087108},
{"learn":[15.49733301],"iteration":736,"passed_time":0.0975936234,"remaining_time":0.02648402263},
{"learn":[15.49378848],"iteration":737,"passed_time":0.09769795463,"remaining_time":0.02634402842},
{"learn":[15.49063769],"iteration":738,"passed_time":0.09780978466,"remaining_time":0.02620613987},
{"learn":[15.48579323],"iteration":739,"passed_time":0.09807477763,"remaining_time":0.02610909621},
{"learn":[15.47956273],"iteration":740,"passed_time":0.09817248304,"remaining_time":0.02596735044},
{"learn":[15.47564226],"iteration":741,"passed_time":0.09830010465,"remaining_time":0.02583358545},
{"learn":[15.47252704],"iteration":742,"passed_time":0.09841185169,"remaining_time":0.0256956921},
{"learn":[15.46633316],"iteration":743,"passed_time":0.09849534947,"remaining_time":0.02555054092},
{"learn":[15.46218944],"iteration":744,"passed_time":0.09861663725,"remaining_time":0.02541529443},
{"learn":[15.45903184],"iteration":745,"passed_time":0.09875738352,"remaining_time":0.02528506736},
{"learn":[15.45287477],"iteration":746,"passed_time":0.09888575511,"remaining_time":0.02515166462},
{"learn":[15.44973347],"iteration":747,"passed_time":0.0989880854,"remaining_time":0.02501169537},
{"learn":[15.44495525],"iteration":748,"passed_time":0.09909574954,"remaining_time":0.02487316544},
{"learn":[15.44145108],"iteration":749,"passed_time":0.09925270438,"remaining_time":0.02474700762},
{"learn":[15.43836713],"iteration":750,"passed_time":0.09935436868,"remaining_time":0.024607074},
{"learn":[15.43501851],"iteration":751,"passed_time":0.09947061559,"remaining_time":0.02447082963},
{"learn":[15.42891039],"iteration":752,"passed_time":0.09962061161,"remaining_time":0.02434288518},
{"learn":[15.42434355],"iteration":753,"passed_time":0.09974244238,"remaining_time":0.02420804636},
{"learn":[15.41961623],"iteration":754,"passed_time":0.09985718934,"remaining_time":0.02407153438},
{"learn":[15.41615866],"iteration":755,"passed_time":0.09999401971,"remaining_time":0.02394036715},
{"learn":[15.41275526],"iteration":756,"passed_time":0.1000989759,"remaining_time":0.0238016059},
{"learn":[15.40901734],"iteration":757,"passed_time":0.1002030982,"remaining_time":0.0236627369},
{"learn":[15.4059873],"iteration":758,"passed_time":0.100322178,"remaining_time":0.0235274673},
{"learn":[15.4027023],"iteration":759,"passed_time":0.1004382999,"remaining_time":0.02339155143},
{"learn":[15.39665828],"iteration":760,"passed_time":0.1005412972,"remaining_time":0.02325265217},
{"learn":[15.39324029],"iteration":761,"passed_time":0.100660378,"remaining_time":0.02311754088},
{"learn":[15.38921103],"iteration":762,"passed_time":0.1008057912,"remaining_time":0.02298847662},
{"learn":[15.38595881],"iteration":763,"passed_time":0.1009034546,"remaining_time":0.02284855712},
{"learn":[15.37995178],"iteration":764,"passed_time":0.1010180345,"remaining_time":0.02271255156},
{"learn":[15.37695912],"iteration":765,"passed_time":0.1011211568,"remaining_time":0.02257404414},
{"learn":[15.37098082],"iteration":766,"passed_time":0.1012549862,"remaining_time":0.02244243502},
{"learn":[15.36502448],"iteration":767,"passed_time":0.1013597335,"remaining_time":0.02230442052},
{"learn":[15.35909003],"iteration":768,"passed_time":0.1014931889,"remaining_time":0.02217276429},
{"learn":[15.35317737],"iteration":769,"passed_time":0.1015971452,"remaining_time":0.02203470551},
{"learn":[15.35012915],"iteration":770,"passed_time":0.1016905177,"remaining_time":0.02189445647},
{"learn":[15.34638212],"iteration":771,"passed_time":0.101791931,"remaining_time":0.02175604743},
{"learn":[15.34178895],"iteration":772,"passed_time":0.1019003861,"remaining_time":0.0216192281},
{"learn":[15.33737048],"iteration":773,"passed_time":0.1019955506,"remaining_time":0.02147968314},
{"learn":[15.33346649],"iteration":774,"passed_time":0.1021659211,"remaining_time":0.02135597318},
{"learn":[15.32760416],"iteration":775,"passed_time":0.1022545857,"remaining_time":0.02121519111},
{"learn":[15.32176338],"iteration":776,"passed_time":0.1023710826,"remaining_time":0.02108027442},
{"learn":[15.3186066],"iteration":777,"passed_time":0.1024785388,"remaining_time":0.02094355741},
{"learn":[15.31279363],"iteration":778,"passed_time":0.1025607456,"remaining_time":0.02080179436},
{"learn":[15.30700203],"iteration":779,"passed_time":0.1026778255,"remaining_time":0.02066720334},
{"learn":[15.3024649],"iteration":780,"passed_time":0.1028013642,"remaining_time":0.02053394727},
{"learn":[15.29811724],"iteration":781,"passed_time":0.1029071114,"remaining_time":0.0203971896},
{"learn":[15.29521888],"iteration":782,"passed_time":0.1030170665,"remaining_time":0.02026133875},
{"learn":[15.29087828],"iteration":783,"passed_time":0.1031423132,"remaining_time":0.02012853816},
{"learn":[15.28512734],"iteration":784,"passed_time":0.10322477,"remaining_time":0.01998747138},
{"learn":[15.27939753],"iteration":785,"passed_time":0.1033221424,"remaining_time":0.01984941921},
{"learn":[15.27368879],"iteration":786,"passed_time":0.1034351814,"remaining_time":0.01971445643},
{"learn":[15.27041676],"iteration":787,"passed_time":0.1035608031,"remaining_time":0.0195819285},
{"learn":[15.26617594],"iteration":788,"passed_time":0.1038070465,"remaining_time":0.01947204422},
{"learn":[15.26049924],"iteration":789,"passed_time":0.1039097528,"remaining_time":0.0193351059},
{"learn":[15.25702419],"iteration":790,"passed_time":0.1040238338,"remaining_time":0.01920035364},
{"learn":[15.25316937],"iteration":791,"passed_time":0.1041784967,"remaining_time":0.01907308336},
{"learn":[15.24752445],"iteration":792,"passed_time":0.1043290347,"remaining_time":0.01894499495},
{"learn":[15.2419003],"iteration":793,"passed_time":0.1044518234,"remaining_time":0.01881185233},
{"learn":[15.23629683],"iteration":794,"passed_time":0.1045698203,"remaining_time":0.01867787985},
{"learn":[15.23071396],"iteration":795,"passed_time":0.1046885671,"remaining_time":0.01854408036},
{"learn":[15.22515164],"iteration":796,"passed_time":0.1048200217,"remaining_time":0.01841255085},
{"learn":[15.22093072],"iteration":797,"passed_time":0.1049083113,"remaining_time":0.01827350285},
{"learn":[15.21766473],"iteration":798,"passed_time":0.1050029338,"remaining_time":0.01813567567},
{"learn":[15.21445836],"iteration":799,"passed_time":0.1050900975,"remaining_time":0.01799667919},
{"learn":[15.20893418],"iteration":800,"passed_time":0.1051722203,"remaining_time":0.01785695626},
{"learn":[15.20343032],"iteration":801,"passed_time":0.105259802,"remaining_time":0.01771829584},
{"learn":[15.19902246],"iteration":802,"passed_time":0.1054177558,"remaining_time":0.01759150595},
{"learn":[15.19597532],"iteration":803,"passed_time":0.1055105033,"remaining_time":0.01745385192},
{"learn":[15.19049951],"iteration":804,"passed_time":0.1055945431,"remaining_time":0.0173148816},
{"learn":[15.18713198],"iteration":805,"passed_time":0.1056868316,"remaining_time":0.01717738827},
{"learn":[15.18168289],"iteration":806,"passed_time":0.1057787452,"remaining_time":0.01703994656},
{"learn":[15.17625385],"iteration":807,"passed_time":0.1059222824,"remaining_time":0.01691085944},
{"learn":[15.1732573],"iteration":808,"passed_time":0.1060245707,"remaining_time":0.0167752102},
{"learn":[15.16785137],"iteration":809,"passed_time":0.1061294849,"remaining_time":0.01664005504},
{"learn":[15.16471729],"iteration":810,"passed_time":0.1062054419,"remaining_time":0.01650047556},
{"learn":[15.15933458],"iteration":811,"passed_time":0.1063032303,"remaining_time":0.01636441353},
{"learn":[15.15397169],"iteration":812,"passed_time":0.1063936449,"remaining_time":0.01622732099},
{"learn":[15.15050075],"iteration":813,"passed_time":0.1066226808,"remaining_time":0.01611128961},
{"learn":[15.14739557],"iteration":814,"passed_time":0.1067580522,"remaining_time":0.01598095997},
{"learn":[15.14205939],"iteration":815,"passed_time":0.1068830069,"remaining_time":0.01584907333},
{"learn":[15.13912033],"iteration":816,"passed_time":0.1070202533,"remaining_time":0.01571900905},
{"learn":[15.13380686],"iteration":817,"passed_time":0.1071306253,"remaining_time":0.01558501762},
{"learn":[15.13057763],"iteration":818,"passed_time":0.1073190783,"remaining_time":0.01546233363},
{"learn":[15.1262638],"iteration":819,"passed_time":0.1074424091,"remaining_time":0.01533019739},
{"learn":[15.12097741],"iteration":820,"passed_time":0.1075721136,"remaining_time":0.01519898317},
{"learn":[15.11784243],"iteration":821,"passed_time":0.1077130679,"remaining_time":0.01506934648},
{"learn":[15.11258171],"iteration":822,"passed_time":0.1078638139,"remaining_time":0.01494103862},
{"learn":[15.10734036],"iteration":823,"passed_time":0.1080211017,"remaining_time":0.01481357341},
{"learn":[15.10211831],"iteration":824,"passed_time":0.1081081404,"remaining_time":0.01467649906},
{"learn":[15.09691549],"iteration":825,"passed_time":0.1082273872,"remaining_time":0.01454387407},
{"learn":[15.09411392],"iteration":826,"passed_time":0.1083560918,"remaining_time":0.01441253942},
{"learn":[15.0895433],"iteration":827,"passed_time":0.1084694218,"remaining_time":0.01427918717},
{"learn":[15.08552882],"iteration":828,"passed_time":0.108575585,"remaining_time":0.01414494955},
{"learn":[15.08215288],"iteration":829,"passed_time":0.1086823742,"remaining_time":0.01401086028},
{"learn":[15.07952189],"iteration":830,"passed_time":0.1087832045,"remaining_time":0.01387607663},
{"learn":[15.07616167],"iteration":831,"passed_time":0.1089220758,"remaining_time":0.01374617543},
{"learn":[15.0710112],"iteration":832,"passed_time":0.1090851545,"remaining_time":0.01361927499},
{"learn":[15.06819962],"iteration":833,"passed_time":0.1091897347,"remaining_time":0.01348506316},
{"learn":[15.0647251],"iteration":834,"passed_time":0.1093358978,"remaining_time":0.01335600189},
{"learn":[15.05960515],"iteration":835,"passed_time":0.1094761441,"remaining_time":0.01322618487},
{"learn":[15.0562774],"iteration":836,"passed_time":0.1096020988,"remaining_time":0.01309463546},
{"learn":[15.05117982],"iteration":837,"passed_time":0.1097251785,"remaining_time":0.01296275975},
{"learn":[15.04787139],"iteration":838,"passed_time":0.1098505092,"remaining_time":0.01283116794},
{"learn":[15.04279607],"iteration":839,"passed_time":0.1099828807,"remaining_time":0.01270040408},
{"learn":[15.0392084],"iteration":840,"passed_time":0.1101137942,"remaining_time":0.01256946997},
{"learn":[15.03526952],"iteration":841,"passed_time":0.1102389579,"remaining_time":0.01243788717},
{"learn":[15.03230514],"iteration":842,"passed_time":0.1103494969,"remaining_time":0.01230468886},
{"learn":[15.02903654],"iteration":843,"passed_time":0.1104756606,"remaining_time":0.01217326592},
{"learn":[15.02399626],"iteration":844,"passed_time":0.1106157399,"remaining_time":0.01204337049},
{"learn":[15.02068911],"iteration":845,"passed_time":0.1107084874,"remaining_time":0.01190835976},
{"learn":[15.01567084],"iteration":846,"passed_time":0.1108391919,"remaining_time":0.01177748202},
{"learn":[15.01243318],"iteration":847,"passed_time":0.1109780632,"remaining_time":0.01164746183},
{"learn":[15.00743679],"iteration":848,"passed_time":0.1110667279,"remaining_time":0.01151221679},
{"learn":[15.0024588],"iteration":849,"passed_time":0.111212808,"remaining_time":0.011382958},
{"learn":[14.99903736],"iteration":850,"passed_time":0.1113023466,"remaining_time":0.01124794572},
{"learn":[14.99612025],"iteration":851,"passed_time":0.111438135,"remaining_time":0.01111765432},
{"learn":[14.99296625],"iteration":852,"passed_time":0.1115218828,"remaining_time":0.01098222527},
{"learn":[14.98802196],"iteration":853,"passed_time":0.1116420046,"remaining_time":0.01085045244},
{"learn":[14.98309587],"iteration":854,"passed_time":0.111741502,"remaining_time":0.01071672885},
{"learn":[14.97818794],"iteration":855,"passed_time":0.1118429163,"remaining_time":0.01058326661},
{"learn":[14.97413104],"iteration":856,"passed_time":0.1119497465,"remaining_time":0.01045038473},
{"learn":[14.96924424],"iteration":857,"passed_time":0.112078993,"remaining_time":0.01031962756},
{"learn":[14.96437544],"iteration":858,"passed_time":0.1122071146,"remaining_time":0.01018877176},
{"learn":[14.96162613],"iteration":859,"passed_time":0.1123483199,"remaining_time":0.01005909376},
{"learn":[14.95761105],"iteration":860,"passed_time":0.112493149,"remaining_time":0.009929708859},
{"learn":[14.95373561],"iteration":861,"passed_time":0.1126147288,"remaining_time":0.009798265269},
{"learn":[14.94972043],"iteration":862,"passed_time":0.1127251429,"remaining_time":0.009665887108},
{"learn":[14.94488547],"iteration":863,"passed_time":0.1128575564,"remaining_time":0.009535418537},
{"learn":[14.94047278],"iteration":864,"passed_time":0.1129948857,"remaining_time":0.009405354651},
{"learn":[14.93662229],"iteration":865,"passed_time":0.1131212574,"remaining_time":0.009274375605},
{"learn":[14.93392805],"iteration":866,"passed_time":0.1132355043,"remaining_time":0.009142428264},
{"learn":[14.93107707],"iteration":867,"passed_time":0.1133467934,"remaining_time":0.009010286572},
{"learn":[14.92627579],"iteration":868,"passed_time":0.1134825818,"remaining_time":0.008880109968},
{"learn":[14.92343985],"iteration":869,"passed_time":0.113626203,"remaining_time":0.008750523678},
{"learn":[14.91865912],"iteration":870,"passed_time":0.1137220754,"remaining_time":0.008617287002},
{"learn":[14.91484669],"iteration":871,"passed_time":0.1138111561,"remaining_time":0.008483629753},
{"learn":[14.91193101],"iteration":872,"passed_time":0.1139092365,"remaining_time":0.008350734403},
{"learn":[14.90717952],"iteration":873,"passed_time":0.1140341912,"remaining_time":0.008219855884},
{"learn":[14.90339198],"iteration":874,"passed_time":0.1141598958,"remaining_time":0.008089044047},
{"learn":[14.89944307],"iteration":875,"passed_time":0.1142926833,"remaining_time":0.007958737079},
{"learn":[14.89471957],"iteration":876,"passed_time":0.1144265967,"remaining_time":0.007828501488},
{"learn":[14.89191844],"iteration":877,"passed_time":0.1146766731,"remaining_time":0.007706063455},
{"learn":[14.88815668],"iteration":878,"passed_time":0.1147781284,"remaining_time":0.007573528382},
{"learn":[14.88420048],"iteration":879,"passed_time":0.1148914174,"remaining_time":0.007441830446},
{"learn":[14.88155116],"iteration":880,"passed_time":0.115019123,"remaining_time":0.00731109068},
{"learn":[14.87826017],"iteration":881,"passed_time":0.1151475366,"remaining_time":0.007180401943},
{"learn":[14.87357633],"iteration":882,"passed_time":0.1152672834,"remaining_time":0.007049188342},
{"learn":[14.87033255],"iteration":883,"passed_time":0.1153844463,"remaining_time":0.006917845764},
{"learn":[14.86660653],"iteration":884,"passed_time":0.1155677335,"remaining_time":0.006790420497},
{"learn":[14.86195597],"iteration":885,"passed_time":0.1157025639,"remaining_time":0.006660079863},
{"learn":[14.85933034],"iteration":886,"passed_time":0.115813061,"remaining_time":0.006528357438},
{"learn":[14.85562764],"iteration":887,"passed_time":0.1159179332,"remaining_time":0.006396372439},
{"learn":[14.8524864],"iteration":888,"passed_time":0.1160880117,"remaining_time":0.006267969133},
{"learn":[14.84987603],"iteration":889,"passed_time":0.1162066755,"remaining_time":0.006136757021},
{"learn":[14.84874763],"iteration":890,"passed_time":0.1163133397,"remaining_time":0.006004953564},
{"learn":[14.84611284],"iteration":891,"passed_time":0.1164492951,"remaining_time":0.005874684168},
{"learn":[14.84149999],"iteration":892,"passed_time":0.1165791666,"remaining_time":0.005744102275},
{"learn":[14.83893907],"iteration":893,"passed_time":0.1166949556,"remaining_time":0.005612844618},
{"learn":[14.83635121],"iteration":894,"passed_time":0.1168179523,"remaining_time":0.005481959772},
{"learn":[14.83268365],"iteration":895,"passed_time":0.1169365321,"remaining_time":0.005350890422},
{"learn":[14.82902914],"iteration":896,"passed_time":0.1170493632,"remaining_time":0.00521959256},
{"learn":[14.82602967],"iteration":897,"passed_time":0.1171482765,"remaining_time":0.005087731386},
{"learn":[14.82285804],"iteration":898,"passed_time":0.1172531487,"remaining_time":0.004956195386},
{"learn":[14.81872946],"iteration":899,"passed_time":0.1173677287,"remaining_time":0.004825117736},
{"learn":[14.81510655],"iteration":900,"passed_time":0.1174996002,"remaining_time":0.0046947676},
{"learn":[14.81056102],"iteration":901,"passed_time":0.1176450133,"remaining_time":0.004564939542},
{"learn":[14.8074218],"iteration":902,"passed_time":0.1177477606,"remaining_time":0.004433470499},
{"learn":[14.80410583],"iteration":903,"passed_time":0.1178733403,"remaining_time":0.004302898484},
{"learn":[14.80298562],"iteration":904,"passed_time":0.1180158365,"remaining_time":0.004172935655},
{"learn":[14.79939356],"iteration":905,"passed_time":0.1181569988,"remaining_time":0.004042899516},
{"learn":[14.79643338],"iteration":906,"passed_time":0.1182822454,"remaining_time":0.003912312418},
{"learn":[14.79331528],"iteration":907,"passed_time":0.1183839097,"remaining_time":0.003780983901},
{"learn":[14.78974482],"iteration":908,"passed_time":0.1184823651,"remaining_time":0.003649621808},
{"learn":[14.78862806],"iteration":909,"passed_time":0.1186349861,"remaining_time":0.003519939147},
{"learn":[14.78608411],"iteration":910,"passed_time":0.1187706495,"remaining_time":0.003389722159},
{"learn":[14.78496932],"iteration":911,"passed_time":0.1188733548,"remaining_time":0.003258589768},
{"learn":[14.78202194],"iteration":912,"passed_time":0.1190098511,"remaining_time":0.003128407916},
{"learn":[14.77899079],"iteration":913,"passed_time":0.1191021817,"remaining_time":0.002997100852},
{"learn":[14.77544187],"iteration":914,"passed_time":0.1191965542,"remaining_time":0.002865928079},
{"learn":[14.77287463],"iteration":915,"passed_time":0.1192985935,"remaining_time":0.002735011422},
{"learn":[14.76840312],"iteration":916,"passed_time":0.1193967579,"remaining_time":0.002604073236},
{"learn":[14.76544853],"iteration":917,"passed_time":0.1195683363,"remaining_time":0.002474725915},
{"learn":[14.76192346],"iteration":918,"passed_time":0.1197034577,"remaining_time":0.002344572621},
{"learn":[14.75918813],"iteration":919,"passed_time":0.1198345382,"remaining_time":0.002214333859},
{"learn":[14.75567969],"iteration":920,"passed_time":0.1199425764,"remaining_time":0.002083692966},
{"learn":[14.75262226],"iteration":921,"passed_time":0.1200264072,"remaining_time":0.001952707275},
{"learn":[14.75034706],"iteration":922,"passed_time":0.1201491129,"remaining_time":0.001822413413},
{"learn":[14.74744769],"iteration":923,"passed_time":0.1202784015,"remaining_time":0.001692228592},
{"learn":[14.743964],"iteration":924,"passed_time":0.1204011902,"remaining_time":0.001561961387},
{"learn":[14.74131678],"iteration":925,"passed_time":0.1205060204,"remaining_time":0.001431497003},
{"learn":[14.73784828],"iteration":926,"passed_time":0.1206140176,"remaining_time":0.001301122088},
{"learn":[14.73439214],"iteration":927,"passed_time":0.1207074731,"remaining_time":0.001170654373},
{"learn":[14.73057211],"iteration":928,"passed_time":0.120823679,"remaining_time":0.001040462252},
{"learn":[14.72754949],"iteration":929,"passed_time":0.1209268013,"remaining_time":0.0009102017299},
{"learn":[14.72644354],"iteration":930,"passed_time":0.121049382,"remaining_time":0.0007801249109},
{"learn":[14.72300848],"iteration":931,"passed_time":0.1211768376,"remaining_time":0.0006500903306},
{"learn":[14.71958564],"iteration":932,"passed_time":0.1213090841,"remaining_time":0.0005200818183},
{"learn":[14.71637241],"iteration":933,"passed_time":0.1214348308,"remaining_time":0.0003900476364},
{"learn":[14.71341739],"iteration":934,"passed_time":0.1215494107,"remaining_time":0.0002599987396},
{"learn":[14.71057079],"iteration":935,"passed_time":0.1216607828,"remaining_time":0.0001299794688},
{"learn":[14.70620648],"iteration":936,"passed_time":0.121767155,"remaining_time":0}
]}